Workbook

Sheet Requerimiento_Cab
A1: Secuencia | B1: CompaniaNombre | C1: ClasificacionNombre | D1: Dirigido a | E1: Almacen | F1: Departamento | G1: CentroCostos | H1: Placa | I1: Proyecto | J1: UnidadNegocio | K1: Dir. Destino | L1: Comentario | M1: CampoReferencia | N1: Moneda
A2: =(IF(LEN(B2)>0,ROW(A2)-1,"")) -> 1 | B2: GRUPO TRANSPESA SAC | C2: Servicios | D2: Compras | E2: Almacén Commodities | F2: OPERACIONES | G2: Tractos | H2: T8H889 | I2: =IF(ISBLANK(Requerimiento_Cab!H2),"",VLOOKUP(Requerimiento_Cab!H2,Tabla1[#All],2,FALSE)) -> 1031100267 | J2: Servicio de Transporte de Carg | K2: Camiones | L2: PEAJES DEL 23.01.23 AL 31.01.23 F030 - 104882 | M2: CONTROL DE FLOTA | N2: LO
A21: =(IF(LEN(B21)>0,ROW(A21)-1,""))
A22: =(IF(LEN(B22)>0,ROW(A22)-1,""))
A23: =(IF(LEN(B23)>0,ROW(A23)-1,""))
A24: =(IF(LEN(B24)>0,ROW(A24)-1,""))
A25: =(IF(LEN(B25)>0,ROW(A25)-1,""))
A26: =(IF(LEN(B26)>0,ROW(A26)-1,""))
A27: =(IF(LEN(B27)>0,ROW(A27)-1,""))
A28: =(IF(LEN(B28)>0,ROW(A28)-1,""))
A29: =(IF(LEN(B29)>0,ROW(A29)-1,""))
A30: =(IF(LEN(B30)>0,ROW(A30)-1,""))
A31: =(IF(LEN(B31)>0,ROW(A31)-1,""))
A32: =(IF(LEN(B32)>0,ROW(A32)-1,""))
... A800: =(IF(LEN(B800)>0,ROW(A800)-1,""))

Sheet GenerarDataCabecera
A1: Secuencia | B1: RequisicionNumero | C1: CompaniaSocio | D1: Clasificacion | E1: ComprasAlmacenFlag | F1: AlmacenCodigo | G1: MonedaCodigo | H1: PreparadaPor | I1: Departamento | J1: PrioridadCodigo | K1: DefaultPrime | L1: DefaultAfe | M1: CuantiaMonetariaPendienteFlag | N1: UnidadNegocio | O1: UnidadReplicacion | P1: LocalForeignFlag | Q1: DireccionDestino | R1: Comentarios | S1: Estado | T1: UltimoUsuario | U1: UltimoUsuarioNumero | V1: TransaccionOperacion | W1: RevisionTecnicaPendienteFlag | X1: DefaultCampoReferencia | Y1: UnidadNegocioCompra
A2: =IF(LEN(Requerimiento_Cab!A2)>0,Requerimiento_Cab!A2,"") -> 1 | B2: =(IF(LEN(C2)>0,ROW(B2)-1,"")) -> 1 | C2: =IF(ISBLANK(Requerimiento_Cab!B2),"",VLOOKUP(Requerimiento_Cab!B2,Tabla3[#All],2,FALSE)) -> 10000000 | D2: =IF(ISBLANK(Requerimiento_Cab!C2),"",VLOOKUP(Requerimiento_Cab!C2,Tabla4[#All],2,FALSE)) -> SER | E2: =IF(ISBLANK(Requerimiento_Cab!D2),"",VLOOKUP(Requerimiento_Cab!D2,Tabla5[#All],2,FALSE)) -> C | F2: =IF(ISBLANK(Requerimiento_Cab!E2),"",VLOOKUP(Requerimiento_Cab!E2,Tabla6[#All],2,FALSE)) -> A007 | G2: =IF(LEN(Requerimiento_Cab!N2)>0,Requerimiento_Cab!N2,"") -> LO | H2: =IF(LEN(C2)>0,"0","") -> 0 | I2: =IF(ISBLANK(Requerimiento_Cab!F2),"",VLOOKUP(Requerimiento_Cab!F2,Tabla7[#All],2,FALSE)) -> OP | J2: =IF(LEN(C2)>0,"1","") -> 1 | K2: =IF(ISBLANK(Requerimiento_Cab!G2),"",VLOOKUP(Requerimiento_Cab!G2,Tabla8[#All],2,FALSE)) -> 010201 | L2: =IF(ISBLANK(Requerimiento_Cab!H2),"",VLOOKUP(Requerimiento_Cab!H2,Tabla1[#All],2,FALSE)) -> 1031100267 | M2: =IF(LEN(C2)>0,"N","") -> N | N2: =IF(ISBLANK(Requerimiento_Cab!J2),"",VLOOKUP(Requerimiento_Cab!J2,Tabla9[#All],2,FALSE)) -> TRAN | O2: =IF(LEN(C2)>0,"TRUJ","") -> TRUJ | P2: =IF(LEN(C2)>0,"L","") -> L | Q2: =IF(ISBLANK(Requerimiento_Cab!K2),"",VLOOKUP(Requerimiento_Cab!K2,Tabla10[#All],2,FALSE)) -> Costos | R2: =IF(LEN(Requerimiento_Cab!L2)>0,Requerimiento_Cab!L2,"") -> PEAJES DEL 23.01.23 AL 31.01.23 F030 - 104882 | S2: =IF(LEN(C2)>0,"RV","") -> RV | T2: =IF(LEN(C2)>0,"DEMO","") -> DEMO | U2: =IF(LEN(C2)>0,"0","") -> 0 | V2: =IF(ISBLANK(Requerimiento_Cab!F2),"",VLOOKUP(Requerimiento_Cab!F2,Tabla7[#All],2,FALSE)) -> OP | W2: =IF(LEN(C2)>0,"N","") -> N | X2: =IF(ISBLANK(Requerimiento_Cab!M2),"",VLOOKUP(Requerimiento_Cab!M2,Tabla2[#All],2,FALSE)) -> 108 | Y2: =IF(ISBLANK(Requerimiento_Cab!J2),"",VLOOKUP(Requerimiento_Cab!J2,Tabla9[#All],2,FALSE)) -> TRAN
A3: =IF(LEN(Requerimiento_Cab!A3)>0,Requerimiento_Cab!A3,"") | B3: =(IF(LEN(C3)>0,ROW(B3)-1,"")) | C3: =IF(ISBLANK(Requerimiento_Cab!B3),"",VLOOKUP(Requerimiento_Cab!B3,Tabla3[#All],2,FALSE)) | D3: =IF(ISBLANK(Requerimiento_Cab!C3),"",VLOOKUP(Requerimiento_Cab!C3,Tabla4[#All],2,FALSE)) | E3: =IF(ISBLANK(Requerimiento_Cab!D3),"",VLOOKUP(Requerimiento_Cab!D3,Tabla5[#All],2,FALSE)) | F3: =IF(ISBLANK(Requerimiento_Cab!E3),"",VLOOKUP(Requerimiento_Cab!E3,Tabla6[#All],2,FALSE)) | G3: =IF(LEN(C3)>0,"LO","") | H3: =IF(LEN(C3)>0,"0","") | I3: =IF(ISBLANK(Requerimiento_Cab!F3),"",VLOOKUP(Requerimiento_Cab!F3,Tabla7[#All],2,FALSE)) | J3: =IF(LEN(C3)>0,"1","") | K3: =IF(ISBLANK(Requerimiento_Cab!G3),"",VLOOKUP(Requerimiento_Cab!G3,Tabla8[#All],2,FALSE)) | L3: =IF(ISBLANK(Requerimiento_Cab!H3),"",VLOOKUP(Requerimiento_Cab!H3,Tabla1[#All],2,FALSE)) | M3: =IF(LEN(C3)>0,"N","") | N3: =IF(ISBLANK(Requerimiento_Cab!J3),"",VLOOKUP(Requerimiento_Cab!J3,Tabla9[#All],2,FALSE)) | O3: =IF(LEN(C3)>0,"TRUJ","") | P3: =IF(LEN(C3)>0,"L","") | Q3: =IF(ISBLANK(Requerimiento_Cab!K3),"",VLOOKUP(Requerimiento_Cab!K3,Tabla10[#All],2,FALSE)) | R3: =IF(LEN(Requerimiento_Cab!L3)>0,Requerimiento_Cab!L3,"") | S3: =IF(LEN(C3)>0,"RV","") | T3: =IF(LEN(C3)>0,"DEMO","") | U3: =IF(LEN(C3)>0,"0","") | V3: =IF(ISBLANK(Requerimiento_Cab!F3),"",VLOOKUP(Requerimiento_Cab!F3,Tabla7[#All],2,FALSE)) | W3: =IF(LEN(C3)>0,"N","") | X3: =IF(ISBLANK(Requerimiento_Cab!M3),"",VLOOKUP(Requerimiento_Cab!M3,Tabla2[#All],2,FALSE)) | Y3: =IF(ISBLANK(Requerimiento_Cab!J3),"",VLOOKUP(Requerimiento_Cab!J3,Tabla9[#All],2,FALSE))
A4: =IF(LEN(Requerimiento_Cab!A4)>0,Requerimiento_Cab!A4,"") | B4: =(IF(LEN(C4)>0,ROW(B4)-1,"")) | C4: =IF(ISBLANK(Requerimiento_Cab!B4),"",VLOOKUP(Requerimiento_Cab!B4,Tabla3[#All],2,FALSE)) | D4: =IF(ISBLANK(Requerimiento_Cab!C4),"",VLOOKUP(Requerimiento_Cab!C4,Tabla4[#All],2,FALSE)) | E4: =IF(ISBLANK(Requerimiento_Cab!D4),"",VLOOKUP(Requerimiento_Cab!D4,Tabla5[#All],2,FALSE)) | F4: =IF(ISBLANK(Requerimiento_Cab!E4),"",VLOOKUP(Requerimiento_Cab!E4,Tabla6[#All],2,FALSE)) | G4: =IF(LEN(C4)>0,"LO","") | H4: =IF(LEN(C4)>0,"0","") | I4: =IF(ISBLANK(Requerimiento_Cab!F4),"",VLOOKUP(Requerimiento_Cab!F4,Tabla7[#All],2,FALSE)) | J4: =IF(LEN(C4)>0,"1","") | K4: =IF(ISBLANK(Requerimiento_Cab!G4),"",VLOOKUP(Requerimiento_Cab!G4,Tabla8[#All],2,FALSE)) | L4: =IF(ISBLANK(Requerimiento_Cab!H4),"",VLOOKUP(Requerimiento_Cab!H4,Tabla1[#All],2,FALSE)) | M4: =IF(LEN(C4)>0,"N","") | N4: =IF(ISBLANK(Requerimiento_Cab!J4),"",VLOOKUP(Requerimiento_Cab!J4,Tabla9[#All],2,FALSE)) | O4: =IF(LEN(C4)>0,"TRUJ","") | P4: =IF(LEN(C4)>0,"L","") | Q4: =IF(ISBLANK(Requerimiento_Cab!K4),"",VLOOKUP(Requerimiento_Cab!K4,Tabla10[#All],2,FALSE)) | R4: =IF(LEN(Requerimiento_Cab!L4)>0,Requerimiento_Cab!L4,"") | S4: =IF(LEN(C4)>0,"RV","") | T4: =IF(LEN(C4)>0,"DEMO","") | U4: =IF(LEN(C4)>0,"0","") | V4: =IF(ISBLANK(Requerimiento_Cab!F4),"",VLOOKUP(Requerimiento_Cab!F4,Tabla7[#All],2,FALSE)) | W4: =IF(LEN(C4)>0,"N","") | X4: =IF(ISBLANK(Requerimiento_Cab!M4),"",VLOOKUP(Requerimiento_Cab!M4,Tabla2[#All],2,FALSE)) | Y4: =IF(ISBLANK(Requerimiento_Cab!J4),"",VLOOKUP(Requerimiento_Cab!J4,Tabla9[#All],2,FALSE))
A5: =IF(LEN(Requerimiento_Cab!A5)>0,Requerimiento_Cab!A5,"") | B5: =(IF(LEN(C5)>0,ROW(B5)-1,"")) | C5: =IF(ISBLANK(Requerimiento_Cab!B5),"",VLOOKUP(Requerimiento_Cab!B5,Tabla3[#All],2,FALSE)) | D5: =IF(ISBLANK(Requerimiento_Cab!C5),"",VLOOKUP(Requerimiento_Cab!C5,Tabla4[#All],2,FALSE)) | E5: =IF(ISBLANK(Requerimiento_Cab!D5),"",VLOOKUP(Requerimiento_Cab!D5,Tabla5[#All],2,FALSE)) | F5: =IF(ISBLANK(Requerimiento_Cab!E5),"",VLOOKUP(Requerimiento_Cab!E5,Tabla6[#All],2,FALSE)) | G5: =IF(LEN(C5)>0,"LO","") | H5: =IF(LEN(C5)>0,"0","") | I5: =IF(ISBLANK(Requerimiento_Cab!F5),"",VLOOKUP(Requerimiento_Cab!F5,Tabla7[#All],2,FALSE)) | J5: =IF(LEN(C5)>0,"1","") | K5: =IF(ISBLANK(Requerimiento_Cab!G5),"",VLOOKUP(Requerimiento_Cab!G5,Tabla8[#All],2,FALSE)) | L5: =IF(ISBLANK(Requerimiento_Cab!H5),"",VLOOKUP(Requerimiento_Cab!H5,Tabla1[#All],2,FALSE)) | M5: =IF(LEN(C5)>0,"N","") | N5: =IF(ISBLANK(Requerimiento_Cab!J5),"",VLOOKUP(Requerimiento_Cab!J5,Tabla9[#All],2,FALSE)) | O5: =IF(LEN(C5)>0,"TRUJ","") | P5: =IF(LEN(C5)>0,"L","") | Q5: =IF(ISBLANK(Requerimiento_Cab!K5),"",VLOOKUP(Requerimiento_Cab!K5,Tabla10[#All],2,FALSE)) | R5: =IF(LEN(Requerimiento_Cab!L5)>0,Requerimiento_Cab!L5,"") | S5: =IF(LEN(C5)>0,"RV","") | T5: =IF(LEN(C5)>0,"DEMO","") | U5: =IF(LEN(C5)>0,"0","") | V5: =IF(ISBLANK(Requerimiento_Cab!F5),"",VLOOKUP(Requerimiento_Cab!F5,Tabla7[#All],2,FALSE)) | W5: =IF(LEN(C5)>0,"N","") | X5: =IF(ISBLANK(Requerimiento_Cab!M5),"",VLOOKUP(Requerimiento_Cab!M5,Tabla2[#All],2,FALSE)) | Y5: =IF(ISBLANK(Requerimiento_Cab!J5),"",VLOOKUP(Requerimiento_Cab!J5,Tabla9[#All],2,FALSE))
A6: =IF(LEN(Requerimiento_Cab!A6)>0,Requerimiento_Cab!A6,"") | B6: =(IF(LEN(C6)>0,ROW(B6)-1,"")) | C6: =IF(ISBLANK(Requerimiento_Cab!B6),"",VLOOKUP(Requerimiento_Cab!B6,Tabla3[#All],2,FALSE)) | D6: =IF(ISBLANK(Requerimiento_Cab!C6),"",VLOOKUP(Requerimiento_Cab!C6,Tabla4[#All],2,FALSE)) | E6: =IF(ISBLANK(Requerimiento_Cab!D6),"",VLOOKUP(Requerimiento_Cab!D6,Tabla5[#All],2,FALSE)) | F6: =IF(ISBLANK(Requerimiento_Cab!E6),"",VLOOKUP(Requerimiento_Cab!E6,Tabla6[#All],2,FALSE)) | G6: =IF(LEN(C6)>0,"LO","") | H6: =IF(LEN(C6)>0,"0","") | I6: =IF(ISBLANK(Requerimiento_Cab!F6),"",VLOOKUP(Requerimiento_Cab!F6,Tabla7[#All],2,FALSE)) | J6: =IF(LEN(C6)>0,"1","") | K6: =IF(ISBLANK(Requerimiento_Cab!G6),"",VLOOKUP(Requerimiento_Cab!G6,Tabla8[#All],2,FALSE)) | L6: =IF(ISBLANK(Requerimiento_Cab!H6),"",VLOOKUP(Requerimiento_Cab!H6,Tabla1[#All],2,FALSE)) | M6: =IF(LEN(C6)>0,"N","") | N6: =IF(ISBLANK(Requerimiento_Cab!J6),"",VLOOKUP(Requerimiento_Cab!J6,Tabla9[#All],2,FALSE)) | O6: =IF(LEN(C6)>0,"TRUJ","") | P6: =IF(LEN(C6)>0,"L","") | Q6: =IF(ISBLANK(Requerimiento_Cab!K6),"",VLOOKUP(Requerimiento_Cab!K6,Tabla10[#All],2,FALSE)) | R6: =IF(LEN(Requerimiento_Cab!L6)>0,Requerimiento_Cab!L6,"") | S6: =IF(LEN(C6)>0,"RV","") | T6: =IF(LEN(C6)>0,"DEMO","") | U6: =IF(LEN(C6)>0,"0","") | V6: =IF(ISBLANK(Requerimiento_Cab!F6),"",VLOOKUP(Requerimiento_Cab!F6,Tabla7[#All],2,FALSE)) | W6: =IF(LEN(C6)>0,"N","") | X6: =IF(ISBLANK(Requerimiento_Cab!M6),"",VLOOKUP(Requerimiento_Cab!M6,Tabla2[#All],2,FALSE)) | Y6: =IF(ISBLANK(Requerimiento_Cab!J6),"",VLOOKUP(Requerimiento_Cab!J6,Tabla9[#All],2,FALSE))
A7: =IF(LEN(Requerimiento_Cab!A7)>0,Requerimiento_Cab!A7,"") | B7: =(IF(LEN(C7)>0,ROW(B7)-1,"")) | C7: =IF(ISBLANK(Requerimiento_Cab!B7),"",VLOOKUP(Requerimiento_Cab!B7,Tabla3[#All],2,FALSE)) | D7: =IF(ISBLANK(Requerimiento_Cab!C7),"",VLOOKUP(Requerimiento_Cab!C7,Tabla4[#All],2,FALSE)) | E7: =IF(ISBLANK(Requerimiento_Cab!D7),"",VLOOKUP(Requerimiento_Cab!D7,Tabla5[#All],2,FALSE)) | F7: =IF(ISBLANK(Requerimiento_Cab!E7),"",VLOOKUP(Requerimiento_Cab!E7,Tabla6[#All],2,FALSE)) | G7: =IF(LEN(C7)>0,"LO","") | H7: =IF(LEN(C7)>0,"0","") | I7: =IF(ISBLANK(Requerimiento_Cab!F7),"",VLOOKUP(Requerimiento_Cab!F7,Tabla7[#All],2,FALSE)) | J7: =IF(LEN(C7)>0,"1","") | K7: =IF(ISBLANK(Requerimiento_Cab!G7),"",VLOOKUP(Requerimiento_Cab!G7,Tabla8[#All],2,FALSE)) | L7: =IF(ISBLANK(Requerimiento_Cab!H7),"",VLOOKUP(Requerimiento_Cab!H7,Tabla1[#All],2,FALSE)) | M7: =IF(LEN(C7)>0,"N","") | N7: =IF(ISBLANK(Requerimiento_Cab!J7),"",VLOOKUP(Requerimiento_Cab!J7,Tabla9[#All],2,FALSE)) | O7: =IF(LEN(C7)>0,"TRUJ","") | P7: =IF(LEN(C7)>0,"L","") | Q7: =IF(ISBLANK(Requerimiento_Cab!K7),"",VLOOKUP(Requerimiento_Cab!K7,Tabla10[#All],2,FALSE)) | R7: =IF(LEN(Requerimiento_Cab!L7)>0,Requerimiento_Cab!L7,"") | S7: =IF(LEN(C7)>0,"RV","") | T7: =IF(LEN(C7)>0,"DEMO","") | U7: =IF(LEN(C7)>0,"0","") | V7: =IF(ISBLANK(Requerimiento_Cab!F7),"",VLOOKUP(Requerimiento_Cab!F7,Tabla7[#All],2,FALSE)) | W7: =IF(LEN(C7)>0,"N","") | X7: =IF(ISBLANK(Requerimiento_Cab!M7),"",VLOOKUP(Requerimiento_Cab!M7,Tabla2[#All],2,FALSE)) | Y7: =IF(ISBLANK(Requerimiento_Cab!J7),"",VLOOKUP(Requerimiento_Cab!J7,Tabla9[#All],2,FALSE))
A8: =IF(LEN(Requerimiento_Cab!A8)>0,Requerimiento_Cab!A8,"") | B8: =(IF(LEN(C8)>0,ROW(B8)-1,"")) | C8: =IF(ISBLANK(Requerimiento_Cab!B8),"",VLOOKUP(Requerimiento_Cab!B8,Tabla3[#All],2,FALSE)) | D8: =IF(ISBLANK(Requerimiento_Cab!C8),"",VLOOKUP(Requerimiento_Cab!C8,Tabla4[#All],2,FALSE)) | E8: =IF(ISBLANK(Requerimiento_Cab!D8),"",VLOOKUP(Requerimiento_Cab!D8,Tabla5[#All],2,FALSE)) | F8: =IF(ISBLANK(Requerimiento_Cab!E8),"",VLOOKUP(Requerimiento_Cab!E8,Tabla6[#All],2,FALSE)) | G8: =IF(LEN(C8)>0,"LO","") | H8: =IF(LEN(C8)>0,"0","") | I8: =IF(ISBLANK(Requerimiento_Cab!F8),"",VLOOKUP(Requerimiento_Cab!F8,Tabla7[#All],2,FALSE)) | J8: =IF(LEN(C8)>0,"1","") | K8: =IF(ISBLANK(Requerimiento_Cab!G8),"",VLOOKUP(Requerimiento_Cab!G8,Tabla8[#All],2,FALSE)) | L8: =IF(ISBLANK(Requerimiento_Cab!H8),"",VLOOKUP(Requerimiento_Cab!H8,Tabla1[#All],2,FALSE)) | M8: =IF(LEN(C8)>0,"N","") | N8: =IF(ISBLANK(Requerimiento_Cab!J8),"",VLOOKUP(Requerimiento_Cab!J8,Tabla9[#All],2,FALSE)) | O8: =IF(LEN(C8)>0,"TRUJ","") | P8: =IF(LEN(C8)>0,"L","") | Q8: =IF(ISBLANK(Requerimiento_Cab!K8),"",VLOOKUP(Requerimiento_Cab!K8,Tabla10[#All],2,FALSE)) | R8: =IF(LEN(Requerimiento_Cab!L8)>0,Requerimiento_Cab!L8,"") | S8: =IF(LEN(C8)>0,"RV","") | T8: =IF(LEN(C8)>0,"DEMO","") | U8: =IF(LEN(C8)>0,"0","") | V8: =IF(ISBLANK(Requerimiento_Cab!F8),"",VLOOKUP(Requerimiento_Cab!F8,Tabla7[#All],2,FALSE)) | W8: =IF(LEN(C8)>0,"N","") | X8: =IF(ISBLANK(Requerimiento_Cab!M8),"",VLOOKUP(Requerimiento_Cab!M8,Tabla2[#All],2,FALSE)) | Y8: =IF(ISBLANK(Requerimiento_Cab!J8),"",VLOOKUP(Requerimiento_Cab!J8,Tabla9[#All],2,FALSE))
A9: =IF(LEN(Requerimiento_Cab!A9)>0,Requerimiento_Cab!A9,"") | B9: =(IF(LEN(C9)>0,ROW(B9)-1,"")) | C9: =IF(ISBLANK(Requerimiento_Cab!B9),"",VLOOKUP(Requerimiento_Cab!B9,Tabla3[#All],2,FALSE)) | D9: =IF(ISBLANK(Requerimiento_Cab!C9),"",VLOOKUP(Requerimiento_Cab!C9,Tabla4[#All],2,FALSE)) | E9: =IF(ISBLANK(Requerimiento_Cab!D9),"",VLOOKUP(Requerimiento_Cab!D9,Tabla5[#All],2,FALSE)) | F9: =IF(ISBLANK(Requerimiento_Cab!E9),"",VLOOKUP(Requerimiento_Cab!E9,Tabla6[#All],2,FALSE)) | G9: =IF(LEN(C9)>0,"LO","") | H9: =IF(LEN(C9)>0,"0","") | I9: =IF(ISBLANK(Requerimiento_Cab!F9),"",VLOOKUP(Requerimiento_Cab!F9,Tabla7[#All],2,FALSE)) | J9: =IF(LEN(C9)>0,"1","") | K9: =IF(ISBLANK(Requerimiento_Cab!G9),"",VLOOKUP(Requerimiento_Cab!G9,Tabla8[#All],2,FALSE)) | L9: =IF(ISBLANK(Requerimiento_Cab!H9),"",VLOOKUP(Requerimiento_Cab!H9,Tabla1[#All],2,FALSE)) | M9: =IF(LEN(C9)>0,"N","") | N9: =IF(ISBLANK(Requerimiento_Cab!J9),"",VLOOKUP(Requerimiento_Cab!J9,Tabla9[#All],2,FALSE)) | O9: =IF(LEN(C9)>0,"TRUJ","") | P9: =IF(LEN(C9)>0,"L","") | Q9: =IF(ISBLANK(Requerimiento_Cab!K9),"",VLOOKUP(Requerimiento_Cab!K9,Tabla10[#All],2,FALSE)) | R9: =IF(LEN(Requerimiento_Cab!L9)>0,Requerimiento_Cab!L9,"") | S9: =IF(LEN(C9)>0,"RV","") | T9: =IF(LEN(C9)>0,"DEMO","") | U9: =IF(LEN(C9)>0,"0","") | V9: =IF(ISBLANK(Requerimiento_Cab!F9),"",VLOOKUP(Requerimiento_Cab!F9,Tabla7[#All],2,FALSE)) | W9: =IF(LEN(C9)>0,"N","") | X9: =IF(ISBLANK(Requerimiento_Cab!M9),"",VLOOKUP(Requerimiento_Cab!M9,Tabla2[#All],2,FALSE)) | Y9: =IF(ISBLANK(Requerimiento_Cab!J9),"",VLOOKUP(Requerimiento_Cab!J9,Tabla9[#All],2,FALSE))
A10: =IF(LEN(Requerimiento_Cab!A10)>0,Requerimiento_Cab!A10,"") | B10: =(IF(LEN(C10)>0,ROW(B10)-1,"")) | C10: =IF(ISBLANK(Requerimiento_Cab!B10),"",VLOOKUP(Requerimiento_Cab!B10,Tabla3[#All],2,FALSE)) | D10: =IF(ISBLANK(Requerimiento_Cab!C10),"",VLOOKUP(Requerimiento_Cab!C10,Tabla4[#All],2,FALSE)) | E10: =IF(ISBLANK(Requerimiento_Cab!D10),"",VLOOKUP(Requerimiento_Cab!D10,Tabla5[#All],2,FALSE)) | F10: =IF(ISBLANK(Requerimiento_Cab!E10),"",VLOOKUP(Requerimiento_Cab!E10,Tabla6[#All],2,FALSE)) | G10: =IF(LEN(C10)>0,"LO","") | H10: =IF(LEN(C10)>0,"0","") | I10: =IF(ISBLANK(Requerimiento_Cab!F10),"",VLOOKUP(Requerimiento_Cab!F10,Tabla7[#All],2,FALSE)) | J10: =IF(LEN(C10)>0,"1","") | K10: =IF(ISBLANK(Requerimiento_Cab!G10),"",VLOOKUP(Requerimiento_Cab!G10,Tabla8[#All],2,FALSE)) | L10: =IF(ISBLANK(Requerimiento_Cab!H10),"",VLOOKUP(Requerimiento_Cab!H10,Tabla1[#All],2,FALSE)) | M10: =IF(LEN(C10)>0,"N","") | N10: =IF(ISBLANK(Requerimiento_Cab!J10),"",VLOOKUP(Requerimiento_Cab!J10,Tabla9[#All],2,FALSE)) | O10: =IF(LEN(C10)>0,"TRUJ","") | P10: =IF(LEN(C10)>0,"L","") | Q10: =IF(ISBLANK(Requerimiento_Cab!K10),"",VLOOKUP(Requerimiento_Cab!K10,Tabla10[#All],2,FALSE)) | R10: =IF(LEN(Requerimiento_Cab!L10)>0,Requerimiento_Cab!L10,"") | S10: =IF(LEN(C10)>0,"RV","") | T10: =IF(LEN(C10)>0,"DEMO","") | U10: =IF(LEN(C10)>0,"0","") | V10: =IF(ISBLANK(Requerimiento_Cab!F10),"",VLOOKUP(Requerimiento_Cab!F10,Tabla7[#All],2,FALSE)) | W10: =IF(LEN(C10)>0,"N","") | X10: =IF(ISBLANK(Requerimiento_Cab!M10),"",VLOOKUP(Requerimiento_Cab!M10,Tabla2[#All],2,FALSE)) | Y10: =IF(ISBLANK(Requerimiento_Cab!J10),"",VLOOKUP(Requerimiento_Cab!J10,Tabla9[#All],2,FALSE))
A11: =IF(LEN(Requerimiento_Cab!A11)>0,Requerimiento_Cab!A11,"") | B11: =(IF(LEN(C11)>0,ROW(B11)-1,"")) | C11: =IF(ISBLANK(Requerimiento_Cab!B11),"",VLOOKUP(Requerimiento_Cab!B11,Tabla3[#All],2,FALSE)) | D11: =IF(ISBLANK(Requerimiento_Cab!C11),"",VLOOKUP(Requerimiento_Cab!C11,Tabla4[#All],2,FALSE)) | E11: =IF(ISBLANK(Requerimiento_Cab!D11),"",VLOOKUP(Requerimiento_Cab!D11,Tabla5[#All],2,FALSE)) | F11: =IF(ISBLANK(Requerimiento_Cab!E11),"",VLOOKUP(Requerimiento_Cab!E11,Tabla6[#All],2,FALSE)) | G11: =IF(LEN(C11)>0,"LO","") | H11: =IF(LEN(C11)>0,"0","") | I11: =IF(ISBLANK(Requerimiento_Cab!F11),"",VLOOKUP(Requerimiento_Cab!F11,Tabla7[#All],2,FALSE)) | J11: =IF(LEN(C11)>0,"1","") | K11: =IF(ISBLANK(Requerimiento_Cab!G11),"",VLOOKUP(Requerimiento_Cab!G11,Tabla8[#All],2,FALSE)) | L11: =IF(ISBLANK(Requerimiento_Cab!H11),"",VLOOKUP(Requerimiento_Cab!H11,Tabla1[#All],2,FALSE)) | M11: =IF(LEN(C11)>0,"N","") | N11: =IF(ISBLANK(Requerimiento_Cab!J11),"",VLOOKUP(Requerimiento_Cab!J11,Tabla9[#All],2,FALSE)) | O11: =IF(LEN(C11)>0,"TRUJ","") | P11: =IF(LEN(C11)>0,"L","") | Q11: =IF(ISBLANK(Requerimiento_Cab!K11),"",VLOOKUP(Requerimiento_Cab!K11,Tabla10[#All],2,FALSE)) | R11: =IF(LEN(Requerimiento_Cab!L11)>0,Requerimiento_Cab!L11,"") | S11: =IF(LEN(C11)>0,"RV","") | T11: =IF(LEN(C11)>0,"DEMO","") | U11: =IF(LEN(C11)>0,"0","") | V11: =IF(ISBLANK(Requerimiento_Cab!F11),"",VLOOKUP(Requerimiento_Cab!F11,Tabla7[#All],2,FALSE)) | W11: =IF(LEN(C11)>0,"N","") | X11: =IF(ISBLANK(Requerimiento_Cab!M11),"",VLOOKUP(Requerimiento_Cab!M11,Tabla2[#All],2,FALSE)) | Y11: =IF(ISBLANK(Requerimiento_Cab!J11),"",VLOOKUP(Requerimiento_Cab!J11,Tabla9[#All],2,FALSE))
A12: =IF(LEN(Requerimiento_Cab!A12)>0,Requerimiento_Cab!A12,"") | B12: =(IF(LEN(C12)>0,ROW(B12)-1,"")) | C12: =IF(ISBLANK(Requerimiento_Cab!B12),"",VLOOKUP(Requerimiento_Cab!B12,Tabla3[#All],2,FALSE)) | D12: =IF(ISBLANK(Requerimiento_Cab!C12),"",VLOOKUP(Requerimiento_Cab!C12,Tabla4[#All],2,FALSE)) | E12: =IF(ISBLANK(Requerimiento_Cab!D12),"",VLOOKUP(Requerimiento_Cab!D12,Tabla5[#All],2,FALSE)) | F12: =IF(ISBLANK(Requerimiento_Cab!E12),"",VLOOKUP(Requerimiento_Cab!E12,Tabla6[#All],2,FALSE)) | G12: =IF(LEN(C12)>0,"LO","") | H12: =IF(LEN(C12)>0,"0","") | I12: =IF(ISBLANK(Requerimiento_Cab!F12),"",VLOOKUP(Requerimiento_Cab!F12,Tabla7[#All],2,FALSE)) | J12: =IF(LEN(C12)>0,"1","") | K12: =IF(ISBLANK(Requerimiento_Cab!G12),"",VLOOKUP(Requerimiento_Cab!G12,Tabla8[#All],2,FALSE)) | L12: =IF(ISBLANK(Requerimiento_Cab!H12),"",VLOOKUP(Requerimiento_Cab!H12,Tabla1[#All],2,FALSE)) | M12: =IF(LEN(C12)>0,"N","") | N12: =IF(ISBLANK(Requerimiento_Cab!J12),"",VLOOKUP(Requerimiento_Cab!J12,Tabla9[#All],2,FALSE)) | O12: =IF(LEN(C12)>0,"TRUJ","") | P12: =IF(LEN(C12)>0,"L","") | Q12: =IF(ISBLANK(Requerimiento_Cab!K12),"",VLOOKUP(Requerimiento_Cab!K12,Tabla10[#All],2,FALSE)) | R12: =IF(LEN(Requerimiento_Cab!L12)>0,Requerimiento_Cab!L12,"") | S12: =IF(LEN(C12)>0,"RV","") | T12: =IF(LEN(C12)>0,"DEMO","") | U12: =IF(LEN(C12)>0,"0","") | V12: =IF(ISBLANK(Requerimiento_Cab!F12),"",VLOOKUP(Requerimiento_Cab!F12,Tabla7[#All],2,FALSE)) | W12: =IF(LEN(C12)>0,"N","") | X12: =IF(ISBLANK(Requerimiento_Cab!M12),"",VLOOKUP(Requerimiento_Cab!M12,Tabla2[#All],2,FALSE)) | Y12: =IF(ISBLANK(Requerimiento_Cab!J12),"",VLOOKUP(Requerimiento_Cab!J12,Tabla9[#All],2,FALSE))
A13: =IF(LEN(Requerimiento_Cab!A13)>0,Requerimiento_Cab!A13,"") | B13: =(IF(LEN(C13)>0,ROW(B13)-1,"")) | C13: =IF(ISBLANK(Requerimiento_Cab!B13),"",VLOOKUP(Requerimiento_Cab!B13,Tabla3[#All],2,FALSE)) | D13: =IF(ISBLANK(Requerimiento_Cab!C13),"",VLOOKUP(Requerimiento_Cab!C13,Tabla4[#All],2,FALSE)) | E13: =IF(ISBLANK(Requerimiento_Cab!D13),"",VLOOKUP(Requerimiento_Cab!D13,Tabla5[#All],2,FALSE)) | F13: =IF(ISBLANK(Requerimiento_Cab!E13),"",VLOOKUP(Requerimiento_Cab!E13,Tabla6[#All],2,FALSE)) | G13: =IF(LEN(C13)>0,"LO","") | H13: =IF(LEN(C13)>0,"0","") | I13: =IF(ISBLANK(Requerimiento_Cab!F13),"",VLOOKUP(Requerimiento_Cab!F13,Tabla7[#All],2,FALSE)) | J13: =IF(LEN(C13)>0,"1","") | K13: =IF(ISBLANK(Requerimiento_Cab!G13),"",VLOOKUP(Requerimiento_Cab!G13,Tabla8[#All],2,FALSE)) | L13: =IF(ISBLANK(Requerimiento_Cab!H13),"",VLOOKUP(Requerimiento_Cab!H13,Tabla1[#All],2,FALSE)) | M13: =IF(LEN(C13)>0,"N","") | N13: =IF(ISBLANK(Requerimiento_Cab!J13),"",VLOOKUP(Requerimiento_Cab!J13,Tabla9[#All],2,FALSE)) | O13: =IF(LEN(C13)>0,"TRUJ","") | P13: =IF(LEN(C13)>0,"L","") | Q13: =IF(ISBLANK(Requerimiento_Cab!K13),"",VLOOKUP(Requerimiento_Cab!K13,Tabla10[#All],2,FALSE)) | R13: =IF(LEN(Requerimiento_Cab!L13)>0,Requerimiento_Cab!L13,"") | S13: =IF(LEN(C13)>0,"RV","") | T13: =IF(LEN(C13)>0,"DEMO","") | U13: =IF(LEN(C13)>0,"0","") | V13: =IF(ISBLANK(Requerimiento_Cab!F13),"",VLOOKUP(Requerimiento_Cab!F13,Tabla7[#All],2,FALSE)) | W13: =IF(LEN(C13)>0,"N","") | X13: =IF(ISBLANK(Requerimiento_Cab!M13),"",VLOOKUP(Requerimiento_Cab!M13,Tabla2[#All],2,FALSE)) | Y13: =IF(ISBLANK(Requerimiento_Cab!J13),"",VLOOKUP(Requerimiento_Cab!J13,Tabla9[#All],2,FALSE))
A14: =IF(LEN(Requerimiento_Cab!A14)>0,Requerimiento_Cab!A14,"") | B14: =(IF(LEN(C14)>0,ROW(B14)-1,"")) | C14: =IF(ISBLANK(Requerimiento_Cab!B14),"",VLOOKUP(Requerimiento_Cab!B14,Tabla3[#All],2,FALSE)) | D14: =IF(ISBLANK(Requerimiento_Cab!C14),"",VLOOKUP(Requerimiento_Cab!C14,Tabla4[#All],2,FALSE)) | E14: =IF(ISBLANK(Requerimiento_Cab!D14),"",VLOOKUP(Requerimiento_Cab!D14,Tabla5[#All],2,FALSE)) | F14: =IF(ISBLANK(Requerimiento_Cab!E14),"",VLOOKUP(Requerimiento_Cab!E14,Tabla6[#All],2,FALSE)) | G14: =IF(LEN(C14)>0,"LO","") | H14: =IF(LEN(C14)>0,"0","") | I14: =IF(ISBLANK(Requerimiento_Cab!F14),"",VLOOKUP(Requerimiento_Cab!F14,Tabla7[#All],2,FALSE)) | J14: =IF(LEN(C14)>0,"1","") | K14: =IF(ISBLANK(Requerimiento_Cab!G14),"",VLOOKUP(Requerimiento_Cab!G14,Tabla8[#All],2,FALSE)) | L14: =IF(ISBLANK(Requerimiento_Cab!H14),"",VLOOKUP(Requerimiento_Cab!H14,Tabla1[#All],2,FALSE)) | M14: =IF(LEN(C14)>0,"N","") | N14: =IF(ISBLANK(Requerimiento_Cab!J14),"",VLOOKUP(Requerimiento_Cab!J14,Tabla9[#All],2,FALSE)) | O14: =IF(LEN(C14)>0,"TRUJ","") | P14: =IF(LEN(C14)>0,"L","") | Q14: =IF(ISBLANK(Requerimiento_Cab!K14),"",VLOOKUP(Requerimiento_Cab!K14,Tabla10[#All],2,FALSE)) | R14: =IF(LEN(Requerimiento_Cab!L14)>0,Requerimiento_Cab!L14,"") | S14: =IF(LEN(C14)>0,"RV","") | T14: =IF(LEN(C14)>0,"DEMO","") | U14: =IF(LEN(C14)>0,"0","") | V14: =IF(ISBLANK(Requerimiento_Cab!F14),"",VLOOKUP(Requerimiento_Cab!F14,Tabla7[#All],2,FALSE)) | W14: =IF(LEN(C14)>0,"N","") | X14: =IF(ISBLANK(Requerimiento_Cab!M14),"",VLOOKUP(Requerimiento_Cab!M14,Tabla2[#All],2,FALSE)) | Y14: =IF(ISBLANK(Requerimiento_Cab!J14),"",VLOOKUP(Requerimiento_Cab!J14,Tabla9[#All],2,FALSE))
... A800: =IF(LEN(Requerimiento_Cab!A800)>0,Requerimiento_Cab!A800,"") | B800: =(IF(LEN(C800)>0,ROW(B800)-1,"")) | C800: =IF(ISBLANK(Requerimiento_Cab!B800),"",VLOOKUP(Requerimiento_Cab!B800,Tabla3[#All],2,FALSE)) | D800: =IF(ISBLANK(Requerimiento_Cab!C800),"",VLOOKUP(Requerimiento_Cab!C800,Tabla4[#All],2,FALSE)) | E800: =IF(ISBLANK(Requerimiento_Cab!D800),"",VLOOKUP(Requerimiento_Cab!D800,Tabla5[#All],2,FALSE)) | F800: =IF(ISBLANK(Requerimiento_Cab!E800),"",VLOOKUP(Requerimiento_Cab!E800,Tabla6[#All],2,FALSE)) | G800: =IF(LEN(C800)>0,"LO","") | H800: =IF(LEN(C800)>0,"0","") | I800: =IF(ISBLANK(Requerimiento_Cab!F800),"",VLOOKUP(Requerimiento_Cab!F800,Tabla7[#All],2,FALSE)) | J800: =IF(LEN(C800)>0,"1","") | K800: =IF(ISBLANK(Requerimiento_Cab!G800),"",VLOOKUP(Requerimiento_Cab!G800,Tabla8[#All],2,FALSE)) | L800: =IF(ISBLANK(Requerimiento_Cab!H800),"",VLOOKUP(Requerimiento_Cab!H800,Tabla1[#All],2,FALSE)) | M800: =IF(LEN(C800)>0,"N","") | N800: =IF(ISBLANK(Requerimiento_Cab!J800),"",VLOOKUP(Requerimiento_Cab!J800,Tabla9[#All],2,FALSE)) | O800: =IF(LEN(C800)>0,"TRUJ","") | P800: =IF(LEN(C800)>0,"L","") | Q800: =IF(ISBLANK(Requerimiento_Cab!K800),"",VLOOKUP(Requerimiento_Cab!K800,Tabla10[#All],2,FALSE)) | R800: =IF(LEN(Requerimiento_Cab!L800)>0,Requerimiento_Cab!L800,"") | S800: =IF(LEN(C800)>0,"RV","") | T800: =IF(LEN(C800)>0,"DEMO","") | U800: =IF(LEN(C800)>0,"0","") | V800: =IF(ISBLANK(Requerimiento_Cab!F800),"",VLOOKUP(Requerimiento_Cab!F800,Tabla7[#All],2,FALSE)) | W800: =IF(LEN(C800)>0,"N","") | X800: =IF(ISBLANK(Requerimiento_Cab!M800),"",VLOOKUP(Requerimiento_Cab!M800,Tabla2[#All],2,FALSE)) | Y800: =IF(ISBLANK(Requerimiento_Cab!J800),"",VLOOKUP(Requerimiento_Cab!J800,Tabla9[#All],2,FALSE))

Sheet Requerimiento_Det
A1: SecuenciaCabecera | B1: SecuenciaDetalle | C1: CompaniaSocio | D1: Codigo Item | E1: Condicion | F1: Commodity | G1: UnidadCodigo | H1: Descripcion | I1: Dirigido a | J1: CantidadPedido | K1: PrecioUnitario | L1: Comentario | M1: CentroCosto | N1: PLACA | O1: Proyecto | P1: Sucursal
A2: =(IF(LEN(C2)>0,1,"")) -> 1 | B2: =(IF(LEN(C2)>0,ROW(B2)-1,"")) -> 1 | C2: GRUPO TRANSPESA SAC | E2: Nuevo | F2: PEAJES | G2: Unidad | H2: Pacanguilla 287213 TRUJILLO PIURA TRUJILLO | I2: Compras | J2: 1 | L2: Pacanguilla 287213 TRUJILLO PIURA TRUJILLO | M2: Tractos | N2: T8H891 | O2: =IF(ISBLANK(Requerimiento_Det!N2),"",VLOOKUP(Requerimiento_Det!N2,Tabla1[#All],2,FALSE)) -> 1031100265 | P2: Base Trujillo
A3: =(IF(LEN(C3)>0,1,"")) -> 1 | B3: =(IF(LEN(C3)>0,ROW(B3)-1,"")) -> 2 | C3: GRUPO TRANSPESA SAC | E3: Nuevo | F3: PEAJES | G3: Unidad | H3: Chicama 287270 TRUJILLO CHICLAYO TRUJILLO | I3: Compras | J3: 1 | L3: Chicama 287270 TRUJILLO CHICLAYO TRUJILLO | M3: Tractos | N3: T8C806 | O3: =IF(ISBLANK(Requerimiento_Det!N3),"",VLOOKUP(Requerimiento_Det!N3,Tabla1[#All],2,FALSE)) -> 1031100257 | P3: Base Trujillo
A4: =(IF(LEN(C4)>0,1,"")) -> 1 | B4: =(IF(LEN(C4)>0,ROW(B4)-1,"")) -> 3 | C4: GRUPO TRANSPESA SAC | E4: Nuevo | F4: PEAJES | G4: Unidad | H4: Pacanguilla 287269 TRUJILLO CHICLAYO TRUJILLO | I4: Compras | J4: 1 | L4: Pacanguilla 287269 TRUJILLO CHICLAYO TRUJILLO | M4: Tractos | N4: T9G847 | O4: =IF(ISBLANK(Requerimiento_Det!N4),"",VLOOKUP(Requerimiento_Det!N4,Tabla1[#All],2,FALSE)) -> 1031100305 | P4: Base Trujillo
A5: =(IF(LEN(C5)>0,1,"")) -> 1 | B5: =(IF(LEN(C5)>0,ROW(B5)-1,"")) -> 4 | C5: GRUPO TRANSPESA SAC | E5: Nuevo | F5: PEAJES | G5: Unidad | H5: Pacanguilla 287203 TRUJILLO PIURA TRUJILLO | I5: Compras | J5: 1 | L5: Pacanguilla 287203 TRUJILLO PIURA TRUJILLO | M5: Tractos | N5: T4T948 | O5: =IF(ISBLANK(Requerimiento_Det!N5),"",VLOOKUP(Requerimiento_Det!N5,Tabla1[#All],2,FALSE)) -> 1031100125 | P5: Base Trujillo
A6: =(IF(LEN(C6)>0,1,"")) -> 1 | B6: =(IF(LEN(C6)>0,ROW(B6)-1,"")) -> 5 | C6: GRUPO TRANSPESA SAC | E6: Nuevo | F6: PEAJES | G6: Unidad | H6: Pacanguilla 287277 TRUJILLO PIURA TRUJILLO | I6: Compras | J6: 1 | L6: Pacanguilla 287277 TRUJILLO PIURA TRUJILLO | M6: Tractos | N6: TBB942 | O6: =IF(ISBLANK(Requerimiento_Det!N6),"",VLOOKUP(Requerimiento_Det!N6,Tabla1[#All],2,FALSE)) -> 1031100351 | P6: Base Trujillo
A7: =(IF(LEN(C7)>0,1,"")) -> 1 | B7: =(IF(LEN(C7)>0,ROW(B7)-1,"")) -> 6 | C7: GRUPO TRANSPESA SAC | E7: Nuevo | F7: PEAJES | G7: Unidad | H7: Sullana 287628 TALARA CHICLAYO TALARA | I7: Compras | J7: 1 | L7: Sullana 287628 TALARA CHICLAYO TALARA | M7: Tractos | N7: T8Z852 | O7: =IF(ISBLANK(Requerimiento_Det!N7),"",VLOOKUP(Requerimiento_Det!N7,Tabla1[#All],2,FALSE)) -> 1031100294 | P7: Base Trujillo
A8: =(IF(LEN(C8)>0,1,"")) -> 1 | B8: =(IF(LEN(C8)>0,ROW(B8)-1,"")) -> 7 | C8: GRUPO TRANSPESA SAC | E8: Nuevo | F8: PEAJES | G8: Unidad | H8: Chicama 287173 TRUJILLO PIURA TRUJILLO | I8: Compras | J8: 1 | L8: Chicama 287173 TRUJILLO PIURA TRUJILLO | M8: Tractos | N8: TAD844 | O8: =IF(ISBLANK(Requerimiento_Det!N8),"",VLOOKUP(Requerimiento_Det!N8,Tabla1[#All],2,FALSE)) -> 1031100323 | P8: Base Trujillo
A9: =(IF(LEN(C9)>0,1,"")) -> 1 | B9: =(IF(LEN(C9)>0,ROW(B9)-1,"")) -> 8 | C9: GRUPO TRANSPESA SAC | E9: Nuevo | F9: PEAJES | G9: Unidad | H9: Pacanguilla 287268 TRUJILLO CHICLAYO TRUJILLO | I9: Compras | J9: 1 | L9: Pacanguilla 287268 TRUJILLO CHICLAYO TRUJILLO | M9: Tractos | N9: TAD868 | O9: =IF(ISBLANK(Requerimiento_Det!N9),"",VLOOKUP(Requerimiento_Det!N9,Tabla1[#All],2,FALSE)) -> 1031100324 | P9: Base Trujillo
A10: =(IF(LEN(C10)>0,1,"")) -> 1 | B10: =(IF(LEN(C10)>0,ROW(B10)-1,"")) -> 9 | C10: GRUPO TRANSPESA SAC | E10: Nuevo | F10: PEAJES | G10: Unidad | H10: Chicama 287321 TRUJILLO PACASMAYO TRUJILLO | I10: Compras | J10: 1 | L10: Chicama 287321 TRUJILLO PACASMAYO TRUJILLO | M10: Tractos | N10: T9G827 | O10: =IF(ISBLANK(Requerimiento_Det!N10),"",VLOOKUP(Requerimiento_Det!N10,Tabla1[#All],2,FALSE)) -> 1031100300 | P10: Base Trujillo
A11: =(IF(LEN(C11)>0,1,"")) -> 1 | B11: =(IF(LEN(C11)>0,ROW(B11)-1,"")) -> 10 | C11: GRUPO TRANSPESA SAC | E11: Nuevo | F11: PEAJES | G11: Unidad | H11: Mórrope 287276 TRUJILLO PIURA TRUJILLO | I11: Compras | J11: 1 | L11: Mórrope 287276 TRUJILLO PIURA TRUJILLO | M11: Tractos | N11: TBH919 | O11: =IF(ISBLANK(Requerimiento_Det!N11),"",VLOOKUP(Requerimiento_Det!N11,Tabla1[#All],2,FALSE)) -> 1031100363 | P11: Base Trujillo
A12: =(IF(LEN(C12)>0,1,"")) -> 1 | B12: =(IF(LEN(C12)>0,ROW(B12)-1,"")) -> 11 | C12: GRUPO TRANSPESA SAC | E12: Nuevo | F12: PEAJES | G12: Unidad | H12: Sullana 287585 TALARA PIURA TALARA | I12: Compras | J12: 1 | L12: Sullana 287585 TALARA PIURA TALARA | M12: Tractos | N12: T8N850 | O12: =IF(ISBLANK(Requerimiento_Det!N12),"",VLOOKUP(Requerimiento_Det!N12,Tabla1[#All],2,FALSE)) -> 1031100278 | P12: Base Trujillo
A13: =(IF(LEN(C13)>0,1,"")) -> 1 | B13: =(IF(LEN(C13)>0,ROW(B13)-1,"")) -> 12 | C13: GRUPO TRANSPESA SAC | E13: Nuevo | F13: PEAJES | G13: Unidad | H13: Pacanguilla 287202 TRUJILLO PIURA TRUJILLO | I13: Compras | J13: 1 | L13: Pacanguilla 287202 TRUJILLO PIURA TRUJILLO | M13: Tractos | N13: TAD873 | O13: =IF(ISBLANK(Requerimiento_Det!N13),"",VLOOKUP(Requerimiento_Det!N13,Tabla1[#All],2,FALSE)) -> 1031100326 | P13: Base Trujillo
... A543: =(IF(LEN(C543)>0,1,"")) -> 1 | B543: =(IF(LEN(C543)>0,ROW(B543)-1,"")) -> 542 | C543: GRUPO TRANSPESA SAC | E543: Nuevo | F543: PEAJES | G543: Unidad | H543: Pacanguilla 287864 TRUJILLO CHICLAYO TRUJILLO | I543: Compras | J543: 1 | L543: Pacanguilla 287864 TRUJILLO CHICLAYO TRUJILLO | M543: Tractos | N543: ADT925 | O543: =IF(ISBLANK(Requerimiento_Det!N543),"",VLOOKUP(Requerimiento_Det!N543,Tabla1[#All],2,FALSE)) -> 1031100339 | P543: Base Trujillo

Sheet GenerarDataDetalle
A1: SecuenciaCabecera | B1: SecuenciaDetalle | C1: CompaniaSocio | D1: Item | E1: Condicion | F1: Commodity | G1: UnidadCodigo | H1: Descripcion | I1: ComprasAlmacenFlag | J1: RedefinidoFlag | K1: CantidadPedida | L1: CantidadOrdenCompra | M1: CantidadRecibida | N1: PrecioUnitario | O1: PrecioxCantidad | P1: CotizacionSecuencia | Q1: CotizacionCantidad | R1: CotizacionPrecioUnitario | S1: CotizacionPrecioUnitarioconIGV | T1: CotizacionProveedor | U1: CotizacionRegistros | V1: ControlPresupuestalFlag | W1: Comentario | X1: CentroCosto | Y1: Estado | Z1: UltimoUsuario | AA1: IGVExoneradoFlag | AB1: GenerarContratoFlag | AC1: CuentaContable | AD1: Afe | AE1: Sucursal
A2: 1 | B2: =IF(LEN(Requerimiento_Det!B2)>0,Requerimiento_Det!B2,"") -> 1 | C2: =IF(ISBLANK(Requerimiento_Det!C2),"",VLOOKUP(Requerimiento_Det!C2,Tabla3[#All],2,FALSE)) -> 10000000 | D2: =IF(LEN(Requerimiento_Det!D2)>0,Requerimiento_Det!D2,"") | E2: =IF(ISBLANK(Requerimiento_Det!E2),"",VLOOKUP(Requerimiento_Det!E2,Tabla13[#All],2,FALSE)) -> 0 | F2: =IF(ISBLANK(Requerimiento_Det!F2),"",VLOOKUP(Requerimiento_Det!F2,Tabla12[#All],2,FALSE)) -> 2806 | G2: =IF(ISBLANK(Requerimiento_Det!G2),"",VLOOKUP(Requerimiento_Det!G2,Tabla14[#All],2,FALSE)) -> UNI | H2: =IF(LEN(Requerimiento_Det!H2)>0,Requerimiento_Det!H2,"") -> Pacanguilla 287213 TRUJILLO PIURA TRUJILLO | I2: =IF(ISBLANK(Requerimiento_Det!I2),"",VLOOKUP(Requerimiento_Det!I2,Tabla5[#All],2,FALSE)) -> C | J2: =IF(LEN(C2)>0,"N","") -> N | K2: =IF(LEN(Requerimiento_Det!J2)>0,Requerimiento_Det!J2,"") -> 1 | L2: =IF(LEN(C2)>0,"0.00","") -> 0.00 | M2: =IF(LEN(C2)>0,"0.00","") -> 0.00 | N2: =IF(LEN(C2)>0,"0.00","") -> 0.00 | O2: =IF(LEN(N2)>0,K2*N2,"") -> 0 | P2: =IF(LEN(C2)>0,"0","") -> 0 | Q2: =IF(LEN(C2)>0,"0","") -> 0 | R2: =IF(LEN(C2)>0,"0.000000","") -> 0.000000 | S2: =IF(LEN(C2)>0,"0.000000","") -> 0.000000 | T2: =IF(LEN(C2)>0,"0","") -> 0 | U2: =IF(LEN(C2)>0,"0","") -> 0 | V2: =IF(LEN(C2)>0,"S","") -> S | W2: =IF(LEN(Requerimiento_Det!L2)>0,Requerimiento_Det!L2,"") -> Pacanguilla 287213 TRUJILLO PIURA TRUJILLO | X2: =IF(ISBLANK(Requerimiento_Det!M2),"",VLOOKUP(Requerimiento_Det!M2,Tabla8[#All],2,FALSE)) -> 010201 | Y2: =IF(LEN(C2)>0,"PR","") -> PR | Z2: =IF(LEN(C2)>0,"DEMO","") -> DEMO | AA2: =IF(LEN(C2)>0,"N","") -> N | AB2: =IF(LEN(C2)>0,"N","") -> N | AC2: =IF(LEN(C2)>0,"9031501","") -> 9031501 | AD2: =IF(ISBLANK(Requerimiento_Det!N2),"",VLOOKUP(Requerimiento_Det!N2,Tabla1[#All],2,FALSE)) -> 1031100265 | AE2: =IF(ISBLANK(Requerimiento_Det!P2),"",VLOOKUP(Requerimiento_Det!P2,Tabla18[#All],2,FALSE)) -> BTRU
A3: 1 | B3: =IF(LEN(Requerimiento_Det!B3)>0,Requerimiento_Det!B3,"") -> 2 | C3: =IF(ISBLANK(Requerimiento_Det!C3),"",VLOOKUP(Requerimiento_Det!C3,Tabla3[#All],2,FALSE)) -> 10000000 | D3: =IF(LEN(Requerimiento_Det!D3)>0,Requerimiento_Det!D3,"") | E3: =IF(ISBLANK(Requerimiento_Det!E3),"",VLOOKUP(Requerimiento_Det!E3,Tabla13[#All],2,FALSE)) -> 0 | F3: =IF(ISBLANK(Requerimiento_Det!F3),"",VLOOKUP(Requerimiento_Det!F3,Tabla12[#All],2,FALSE)) -> 2806 | G3: =IF(ISBLANK(Requerimiento_Det!G3),"",VLOOKUP(Requerimiento_Det!G3,Tabla14[#All],2,FALSE)) -> UNI | H3: =IF(LEN(Requerimiento_Det!H3)>0,Requerimiento_Det!H3,"") -> Chicama 287270 TRUJILLO CHICLAYO TRUJILLO | I3: =IF(ISBLANK(Requerimiento_Det!I3),"",VLOOKUP(Requerimiento_Det!I3,Tabla5[#All],2,FALSE)) -> C | J3: =IF(LEN(C3)>0,"N","") -> N | K3: =IF(LEN(Requerimiento_Det!J3)>0,Requerimiento_Det!J3,"") -> 1 | L3: =IF(LEN(C3)>0,"0.00","") -> 0.00 | M3: =IF(LEN(C3)>0,"0.00","") -> 0.00 | N3: =IF(LEN(C3)>0,"0.00","") -> 0.00 | O3: =IF(LEN(N3)>0,K3*N3,"") -> 0 | P3: =IF(LEN(C3)>0,"0","") -> 0 | Q3: =IF(LEN(C3)>0,"0","") -> 0 | R3: =IF(LEN(C3)>0,"0.000000","") -> 0.000000 | S3: =IF(LEN(C3)>0,"0.000000","") -> 0.000000 | T3: =IF(LEN(C3)>0,"0","") -> 0 | U3: =IF(LEN(C3)>0,"0","") -> 0 | V3: =IF(LEN(C3)>0,"S","") -> S | W3: =IF(LEN(Requerimiento_Det!L3)>0,Requerimiento_Det!L3,"") -> Chicama 287270 TRUJILLO CHICLAYO TRUJILLO | X3: =IF(ISBLANK(Requerimiento_Det!M3),"",VLOOKUP(Requerimiento_Det!M3,Tabla8[#All],2,FALSE)) -> 010201 | Y3: =IF(LEN(C3)>0,"PR","") -> PR | Z3: =IF(LEN(C3)>0,"DEMO","") -> DEMO | AA3: =IF(LEN(C3)>0,"N","") -> N | AB3: =IF(LEN(C3)>0,"N","") -> N | AC3: =IF(LEN(C3)>0,"9031501","") -> 9031501 | AD3: =IF(ISBLANK(Requerimiento_Det!N3),"",VLOOKUP(Requerimiento_Det!N3,Tabla1[#All],2,FALSE)) -> 1031100257 | AE3: =IF(ISBLANK(Requerimiento_Det!P3),"",VLOOKUP(Requerimiento_Det!P3,Tabla18[#All],2,FALSE)) -> BTRU
A4: 1 | B4: =IF(LEN(Requerimiento_Det!B4)>0,Requerimiento_Det!B4,"") -> 3 | C4: =IF(ISBLANK(Requerimiento_Det!C4),"",VLOOKUP(Requerimiento_Det!C4,Tabla3[#All],2,FALSE)) -> 10000000 | D4: =IF(LEN(Requerimiento_Det!D4)>0,Requerimiento_Det!D4,"") | E4: =IF(ISBLANK(Requerimiento_Det!E4),"",VLOOKUP(Requerimiento_Det!E4,Tabla13[#All],2,FALSE)) -> 0 | F4: =IF(ISBLANK(Requerimiento_Det!F4),"",VLOOKUP(Requerimiento_Det!F4,Tabla12[#All],2,FALSE)) -> 2806 | G4: =IF(ISBLANK(Requerimiento_Det!G4),"",VLOOKUP(Requerimiento_Det!G4,Tabla14[#All],2,FALSE)) -> UNI | H4: =IF(LEN(Requerimiento_Det!H4)>0,Requerimiento_Det!H4,"") -> Pacanguilla 287269 TRUJILLO CHICLAYO TRUJILLO | I4: =IF(ISBLANK(Requerimiento_Det!I4),"",VLOOKUP(Requerimiento_Det!I4,Tabla5[#All],2,FALSE)) -> C | J4: =IF(LEN(C4)>0,"N","") -> N | K4: =IF(LEN(Requerimiento_Det!J4)>0,Requerimiento_Det!J4,"") -> 1 | L4: =IF(LEN(C4)>0,"0.00","") -> 0.00 | M4: =IF(LEN(C4)>0,"0.00","") -> 0.00 | N4: =IF(LEN(C4)>0,"0.00","") -> 0.00 | O4: =IF(LEN(N4)>0,K4*N4,"") -> 0 | P4: =IF(LEN(C4)>0,"0","") -> 0 | Q4: =IF(LEN(C4)>0,"0","") -> 0 | R4: =IF(LEN(C4)>0,"0.000000","") -> 0.000000 | S4: =IF(LEN(C4)>0,"0.000000","") -> 0.000000 | T4: =IF(LEN(C4)>0,"0","") -> 0 | U4: =IF(LEN(C4)>0,"0","") -> 0 | V4: =IF(LEN(C4)>0,"S","") -> S | W4: =IF(LEN(Requerimiento_Det!L4)>0,Requerimiento_Det!L4,"") -> Pacanguilla 287269 TRUJILLO CHICLAYO TRUJILLO | X4: =IF(ISBLANK(Requerimiento_Det!M4),"",VLOOKUP(Requerimiento_Det!M4,Tabla8[#All],2,FALSE)) -> 010201 | Y4: =IF(LEN(C4)>0,"PR","") -> PR | Z4: =IF(LEN(C4)>0,"DEMO","") -> DEMO | AA4: =IF(LEN(C4)>0,"N","") -> N | AB4: =IF(LEN(C4)>0,"N","") -> N | AC4: =IF(LEN(C4)>0,"9031501","") -> 9031501 | AD4: =IF(ISBLANK(Requerimiento_Det!N4),"",VLOOKUP(Requerimiento_Det!N4,Tabla1[#All],2,FALSE)) -> 1031100305 | AE4: =IF(ISBLANK(Requerimiento_Det!P4),"",VLOOKUP(Requerimiento_Det!P4,Tabla18[#All],2,FALSE)) -> BTRU
A5: 1 | B5: =IF(LEN(Requerimiento_Det!B5)>0,Requerimiento_Det!B5,"") -> 4 | C5: =IF(ISBLANK(Requerimiento_Det!C5),"",VLOOKUP(Requerimiento_Det!C5,Tabla3[#All],2,FALSE)) -> 10000000 | D5: =IF(LEN(Requerimiento_Det!D5)>0,Requerimiento_Det!D5,"") | E5: =IF(ISBLANK(Requerimiento_Det!E5),"",VLOOKUP(Requerimiento_Det!E5,Tabla13[#All],2,FALSE)) -> 0 | F5: =IF(ISBLANK(Requerimiento_Det!F5),"",VLOOKUP(Requerimiento_Det!F5,Tabla12[#All],2,FALSE)) -> 2806 | G5: =IF(ISBLANK(Requerimiento_Det!G5),"",VLOOKUP(Requerimiento_Det!G5,Tabla14[#All],2,FALSE)) -> UNI | H5: =IF(LEN(Requerimiento_Det!H5)>0,Requerimiento_Det!H5,"") -> Pacanguilla 287203 TRUJILLO PIURA TRUJILLO | I5: =IF(ISBLANK(Requerimiento_Det!I5),"",VLOOKUP(Requerimiento_Det!I5,Tabla5[#All],2,FALSE)) -> C | J5: =IF(LEN(C5)>0,"N","") -> N | K5: =IF(LEN(Requerimiento_Det!J5)>0,Requerimiento_Det!J5,"") -> 1 | L5: =IF(LEN(C5)>0,"0.00","") -> 0.00 | M5: =IF(LEN(C5)>0,"0.00","") -> 0.00 | N5: =IF(LEN(C5)>0,"0.00","") -> 0.00 | O5: =IF(LEN(N5)>0,K5*N5,"") -> 0 | P5: =IF(LEN(C5)>0,"0","") -> 0 | Q5: =IF(LEN(C5)>0,"0","") -> 0 | R5: =IF(LEN(C5)>0,"0.000000","") -> 0.000000 | S5: =IF(LEN(C5)>0,"0.000000","") -> 0.000000 | T5: =IF(LEN(C5)>0,"0","") -> 0 | U5: =IF(LEN(C5)>0,"0","") -> 0 | V5: =IF(LEN(C5)>0,"S","") -> S | W5: =IF(LEN(Requerimiento_Det!L5)>0,Requerimiento_Det!L5,"") -> Pacanguilla 287203 TRUJILLO PIURA TRUJILLO | X5: =IF(ISBLANK(Requerimiento_Det!M5),"",VLOOKUP(Requerimiento_Det!M5,Tabla8[#All],2,FALSE)) -> 010201 | Y5: =IF(LEN(C5)>0,"PR","") -> PR | Z5: =IF(LEN(C5)>0,"DEMO","") -> DEMO | AA5: =IF(LEN(C5)>0,"N","") -> N | AB5: =IF(LEN(C5)>0,"N","") -> N | AC5: =IF(LEN(C5)>0,"9031501","") -> 9031501 | AD5: =IF(ISBLANK(Requerimiento_Det!N5),"",VLOOKUP(Requerimiento_Det!N5,Tabla1[#All],2,FALSE)) -> 1031100125 | AE5: =IF(ISBLANK(Requerimiento_Det!P5),"",VLOOKUP(Requerimiento_Det!P5,Tabla18[#All],2,FALSE)) -> BTRU
A6: 1 | B6: =IF(LEN(Requerimiento_Det!B6)>0,Requerimiento_Det!B6,"") -> 5 | C6: =IF(ISBLANK(Requerimiento_Det!C6),"",VLOOKUP(Requerimiento_Det!C6,Tabla3[#All],2,FALSE)) -> 10000000 | D6: =IF(LEN(Requerimiento_Det!D6)>0,Requerimiento_Det!D6,"") | E6: =IF(ISBLANK(Requerimiento_Det!E6),"",VLOOKUP(Requerimiento_Det!E6,Tabla13[#All],2,FALSE)) -> 0 | F6: =IF(ISBLANK(Requerimiento_Det!F6),"",VLOOKUP(Requerimiento_Det!F6,Tabla12[#All],2,FALSE)) -> 2806 | G6: =IF(ISBLANK(Requerimiento_Det!G6),"",VLOOKUP(Requerimiento_Det!G6,Tabla14[#All],2,FALSE)) -> UNI | H6: =IF(LEN(Requerimiento_Det!H6)>0,Requerimiento_Det!H6,"") -> Pacanguilla 287277 TRUJILLO PIURA TRUJILLO | I6: =IF(ISBLANK(Requerimiento_Det!I6),"",VLOOKUP(Requerimiento_Det!I6,Tabla5[#All],2,FALSE)) -> C | J6: =IF(LEN(C6)>0,"N","") -> N | K6: =IF(LEN(Requerimiento_Det!J6)>0,Requerimiento_Det!J6,"") -> 1 | L6: =IF(LEN(C6)>0,"0.00","") -> 0.00 | M6: =IF(LEN(C6)>0,"0.00","") -> 0.00 | N6: =IF(LEN(C6)>0,"0.00","") -> 0.00 | O6: =IF(LEN(N6)>0,K6*N6,"") -> 0 | P6: =IF(LEN(C6)>0,"0","") -> 0 | Q6: =IF(LEN(C6)>0,"0","") -> 0 | R6: =IF(LEN(C6)>0,"0.000000","") -> 0.000000 | S6: =IF(LEN(C6)>0,"0.000000","") -> 0.000000 | T6: =IF(LEN(C6)>0,"0","") -> 0 | U6: =IF(LEN(C6)>0,"0","") -> 0 | V6: =IF(LEN(C6)>0,"S","") -> S | W6: =IF(LEN(Requerimiento_Det!L6)>0,Requerimiento_Det!L6,"") -> Pacanguilla 287277 TRUJILLO PIURA TRUJILLO | X6: =IF(ISBLANK(Requerimiento_Det!M6),"",VLOOKUP(Requerimiento_Det!M6,Tabla8[#All],2,FALSE)) -> 010201 | Y6: =IF(LEN(C6)>0,"PR","") -> PR | Z6: =IF(LEN(C6)>0,"DEMO","") -> DEMO | AA6: =IF(LEN(C6)>0,"N","") -> N | AB6: =IF(LEN(C6)>0,"N","") -> N | AC6: =IF(LEN(C6)>0,"9031501","") -> 9031501 | AD6: =IF(ISBLANK(Requerimiento_Det!N6),"",VLOOKUP(Requerimiento_Det!N6,Tabla1[#All],2,FALSE)) -> 1031100351 | AE6: =IF(ISBLANK(Requerimiento_Det!P6),"",VLOOKUP(Requerimiento_Det!P6,Tabla18[#All],2,FALSE)) -> BTRU
A7: 1 | B7: =IF(LEN(Requerimiento_Det!B7)>0,Requerimiento_Det!B7,"") -> 6 | C7: =IF(ISBLANK(Requerimiento_Det!C7),"",VLOOKUP(Requerimiento_Det!C7,Tabla3[#All],2,FALSE)) -> 10000000 | D7: =IF(LEN(Requerimiento_Det!D7)>0,Requerimiento_Det!D7,"") | E7: =IF(ISBLANK(Requerimiento_Det!E7),"",VLOOKUP(Requerimiento_Det!E7,Tabla13[#All],2,FALSE)) -> 0 | F7: =IF(ISBLANK(Requerimiento_Det!F7),"",VLOOKUP(Requerimiento_Det!F7,Tabla12[#All],2,FALSE)) -> 2806 | G7: =IF(ISBLANK(Requerimiento_Det!G7),"",VLOOKUP(Requerimiento_Det!G7,Tabla14[#All],2,FALSE)) -> UNI | H7: =IF(LEN(Requerimiento_Det!H7)>0,Requerimiento_Det!H7,"") -> Sullana 287628 TALARA CHICLAYO TALARA | I7: =IF(ISBLANK(Requerimiento_Det!I7),"",VLOOKUP(Requerimiento_Det!I7,Tabla5[#All],2,FALSE)) -> C | J7: =IF(LEN(C7)>0,"N","") -> N | K7: =IF(LEN(Requerimiento_Det!J7)>0,Requerimiento_Det!J7,"") -> 1 | L7: =IF(LEN(C7)>0,"0.00","") -> 0.00 | M7: =IF(LEN(C7)>0,"0.00","") -> 0.00 | N7: =IF(LEN(C7)>0,"0.00","") -> 0.00 | O7: =IF(LEN(N7)>0,K7*N7,"") -> 0 | P7: =IF(LEN(C7)>0,"0","") -> 0 | Q7: =IF(LEN(C7)>0,"0","") -> 0 | R7: =IF(LEN(C7)>0,"0.000000","") -> 0.000000 | S7: =IF(LEN(C7)>0,"0.000000","") -> 0.000000 | T7: =IF(LEN(C7)>0,"0","") -> 0 | U7: =IF(LEN(C7)>0,"0","") -> 0 | V7: =IF(LEN(C7)>0,"S","") -> S | W7: =IF(LEN(Requerimiento_Det!L7)>0,Requerimiento_Det!L7,"") -> Sullana 287628 TALARA CHICLAYO TALARA | X7: =IF(ISBLANK(Requerimiento_Det!M7),"",VLOOKUP(Requerimiento_Det!M7,Tabla8[#All],2,FALSE)) -> 010201 | Y7: =IF(LEN(C7)>0,"PR","") -> PR | Z7: =IF(LEN(C7)>0,"DEMO","") -> DEMO | AA7: =IF(LEN(C7)>0,"N","") -> N | AB7: =IF(LEN(C7)>0,"N","") -> N | AC7: =IF(LEN(C7)>0,"9031501","") -> 9031501 | AD7: =IF(ISBLANK(Requerimiento_Det!N7),"",VLOOKUP(Requerimiento_Det!N7,Tabla1[#All],2,FALSE)) -> 1031100294 | AE7: =IF(ISBLANK(Requerimiento_Det!P7),"",VLOOKUP(Requerimiento_Det!P7,Tabla18[#All],2,FALSE)) -> BTRU
A8: 1 | B8: =IF(LEN(Requerimiento_Det!B8)>0,Requerimiento_Det!B8,"") -> 7 | C8: =IF(ISBLANK(Requerimiento_Det!C8),"",VLOOKUP(Requerimiento_Det!C8,Tabla3[#All],2,FALSE)) -> 10000000 | D8: =IF(LEN(Requerimiento_Det!D8)>0,Requerimiento_Det!D8,"") | E8: =IF(ISBLANK(Requerimiento_Det!E8),"",VLOOKUP(Requerimiento_Det!E8,Tabla13[#All],2,FALSE)) -> 0 | F8: =IF(ISBLANK(Requerimiento_Det!F8),"",VLOOKUP(Requerimiento_Det!F8,Tabla12[#All],2,FALSE)) -> 2806 | G8: =IF(ISBLANK(Requerimiento_Det!G8),"",VLOOKUP(Requerimiento_Det!G8,Tabla14[#All],2,FALSE)) -> UNI | H8: =IF(LEN(Requerimiento_Det!H8)>0,Requerimiento_Det!H8,"") -> Chicama 287173 TRUJILLO PIURA TRUJILLO | I8: =IF(ISBLANK(Requerimiento_Det!I8),"",VLOOKUP(Requerimiento_Det!I8,Tabla5[#All],2,FALSE)) -> C | J8: =IF(LEN(C8)>0,"N","") -> N | K8: =IF(LEN(Requerimiento_Det!J8)>0,Requerimiento_Det!J8,"") -> 1 | L8: =IF(LEN(C8)>0,"0.00","") -> 0.00 | M8: =IF(LEN(C8)>0,"0.00","") -> 0.00 | N8: =IF(LEN(C8)>0,"0.00","") -> 0.00 | O8: =IF(LEN(N8)>0,K8*N8,"") -> 0 | P8: =IF(LEN(C8)>0,"0","") -> 0 | Q8: =IF(LEN(C8)>0,"0","") -> 0 | R8: =IF(LEN(C8)>0,"0.000000","") -> 0.000000 | S8: =IF(LEN(C8)>0,"0.000000","") -> 0.000000 | T8: =IF(LEN(C8)>0,"0","") -> 0 | U8: =IF(LEN(C8)>0,"0","") -> 0 | V8: =IF(LEN(C8)>0,"S","") -> S | W8: =IF(LEN(Requerimiento_Det!L8)>0,Requerimiento_Det!L8,"") -> Chicama 287173 TRUJILLO PIURA TRUJILLO | X8: =IF(ISBLANK(Requerimiento_Det!M8),"",VLOOKUP(Requerimiento_Det!M8,Tabla8[#All],2,FALSE)) -> 010201 | Y8: =IF(LEN(C8)>0,"PR","") -> PR | Z8: =IF(LEN(C8)>0,"DEMO","") -> DEMO | AA8: =IF(LEN(C8)>0,"N","") -> N | AB8: =IF(LEN(C8)>0,"N","") -> N | AC8: =IF(LEN(C8)>0,"9031501","") -> 9031501 | AD8: =IF(ISBLANK(Requerimiento_Det!N8),"",VLOOKUP(Requerimiento_Det!N8,Tabla1[#All],2,FALSE)) -> 1031100323 | AE8: =IF(ISBLANK(Requerimiento_Det!P8),"",VLOOKUP(Requerimiento_Det!P8,Tabla18[#All],2,FALSE)) -> BTRU
A9: 1 | B9: =IF(LEN(Requerimiento_Det!B9)>0,Requerimiento_Det!B9,"") -> 8 | C9: =IF(ISBLANK(Requerimiento_Det!C9),"",VLOOKUP(Requerimiento_Det!C9,Tabla3[#All],2,FALSE)) -> 10000000 | D9: =IF(LEN(Requerimiento_Det!D9)>0,Requerimiento_Det!D9,"") | E9: =IF(ISBLANK(Requerimiento_Det!E9),"",VLOOKUP(Requerimiento_Det!E9,Tabla13[#All],2,FALSE)) -> 0 | F9: =IF(ISBLANK(Requerimiento_Det!F9),"",VLOOKUP(Requerimiento_Det!F9,Tabla12[#All],2,FALSE)) -> 2806 | G9: =IF(ISBLANK(Requerimiento_Det!G9),"",VLOOKUP(Requerimiento_Det!G9,Tabla14[#All],2,FALSE)) -> UNI | H9: =IF(LEN(Requerimiento_Det!H9)>0,Requerimiento_Det!H9,"") -> Pacanguilla 287268 TRUJILLO CHICLAYO TRUJILLO | I9: =IF(ISBLANK(Requerimiento_Det!I9),"",VLOOKUP(Requerimiento_Det!I9,Tabla5[#All],2,FALSE)) -> C | J9: =IF(LEN(C9)>0,"N","") -> N | K9: =IF(LEN(Requerimiento_Det!J9)>0,Requerimiento_Det!J9,"") -> 1 | L9: =IF(LEN(C9)>0,"0.00","") -> 0.00 | M9: =IF(LEN(C9)>0,"0.00","") -> 0.00 | N9: =IF(LEN(C9)>0,"0.00","") -> 0.00 | O9: =IF(LEN(N9)>0,K9*N9,"") -> 0 | P9: =IF(LEN(C9)>0,"0","") -> 0 | Q9: =IF(LEN(C9)>0,"0","") -> 0 | R9: =IF(LEN(C9)>0,"0.000000","") -> 0.000000 | S9: =IF(LEN(C9)>0,"0.000000","") -> 0.000000 | T9: =IF(LEN(C9)>0,"0","") -> 0 | U9: =IF(LEN(C9)>0,"0","") -> 0 | V9: =IF(LEN(C9)>0,"S","") -> S | W9: =IF(LEN(Requerimiento_Det!L9)>0,Requerimiento_Det!L9,"") -> Pacanguilla 287268 TRUJILLO CHICLAYO TRUJILLO | X9: =IF(ISBLANK(Requerimiento_Det!M9),"",VLOOKUP(Requerimiento_Det!M9,Tabla8[#All],2,FALSE)) -> 010201 | Y9: =IF(LEN(C9)>0,"PR","") -> PR | Z9: =IF(LEN(C9)>0,"DEMO","") -> DEMO | AA9: =IF(LEN(C9)>0,"N","") -> N | AB9: =IF(LEN(C9)>0,"N","") -> N | AC9: =IF(LEN(C9)>0,"9031501","") -> 9031501 | AD9: =IF(ISBLANK(Requerimiento_Det!N9),"",VLOOKUP(Requerimiento_Det!N9,Tabla1[#All],2,FALSE)) -> 1031100324 | AE9: =IF(ISBLANK(Requerimiento_Det!P9),"",VLOOKUP(Requerimiento_Det!P9,Tabla18[#All],2,FALSE)) -> BTRU
A10: 1 | B10: =IF(LEN(Requerimiento_Det!B10)>0,Requerimiento_Det!B10,"") -> 9 | C10: =IF(ISBLANK(Requerimiento_Det!C10),"",VLOOKUP(Requerimiento_Det!C10,Tabla3[#All],2,FALSE)) -> 10000000 | D10: =IF(LEN(Requerimiento_Det!D10)>0,Requerimiento_Det!D10,"") | E10: =IF(ISBLANK(Requerimiento_Det!E10),"",VLOOKUP(Requerimiento_Det!E10,Tabla13[#All],2,FALSE)) -> 0 | F10: =IF(ISBLANK(Requerimiento_Det!F10),"",VLOOKUP(Requerimiento_Det!F10,Tabla12[#All],2,FALSE)) -> 2806 | G10: =IF(ISBLANK(Requerimiento_Det!G10),"",VLOOKUP(Requerimiento_Det!G10,Tabla14[#All],2,FALSE)) -> UNI | H10: =IF(LEN(Requerimiento_Det!H10)>0,Requerimiento_Det!H10,"") -> Chicama 287321 TRUJILLO PACASMAYO TRUJILLO | I10: =IF(ISBLANK(Requerimiento_Det!I10),"",VLOOKUP(Requerimiento_Det!I10,Tabla5[#All],2,FALSE)) -> C | J10: =IF(LEN(C10)>0,"N","") -> N | K10: =IF(LEN(Requerimiento_Det!J10)>0,Requerimiento_Det!J10,"") -> 1 | L10: =IF(LEN(C10)>0,"0.00","") -> 0.00 | M10: =IF(LEN(C10)>0,"0.00","") -> 0.00 | N10: =IF(LEN(C10)>0,"0.00","") -> 0.00 | O10: =IF(LEN(N10)>0,K10*N10,"") -> 0 | P10: =IF(LEN(C10)>0,"0","") -> 0 | Q10: =IF(LEN(C10)>0,"0","") -> 0 | R10: =IF(LEN(C10)>0,"0.000000","") -> 0.000000 | S10: =IF(LEN(C10)>0,"0.000000","") -> 0.000000 | T10: =IF(LEN(C10)>0,"0","") -> 0 | U10: =IF(LEN(C10)>0,"0","") -> 0 | V10: =IF(LEN(C10)>0,"S","") -> S | W10: =IF(LEN(Requerimiento_Det!L10)>0,Requerimiento_Det!L10,"") -> Chicama 287321 TRUJILLO PACASMAYO TRUJILLO | X10: =IF(ISBLANK(Requerimiento_Det!M10),"",VLOOKUP(Requerimiento_Det!M10,Tabla8[#All],2,FALSE)) -> 010201 | Y10: =IF(LEN(C10)>0,"PR","") -> PR | Z10: =IF(LEN(C10)>0,"DEMO","") -> DEMO | AA10: =IF(LEN(C10)>0,"N","") -> N | AB10: =IF(LEN(C10)>0,"N","") -> N | AC10: =IF(LEN(C10)>0,"9031501","") -> 9031501 | AD10: =IF(ISBLANK(Requerimiento_Det!N10),"",VLOOKUP(Requerimiento_Det!N10,Tabla1[#All],2,FALSE)) -> 1031100300 | AE10: =IF(ISBLANK(Requerimiento_Det!P10),"",VLOOKUP(Requerimiento_Det!P10,Tabla18[#All],2,FALSE)) -> BTRU
A11: 1 | B11: =IF(LEN(Requerimiento_Det!B11)>0,Requerimiento_Det!B11,"") -> 10 | C11: =IF(ISBLANK(Requerimiento_Det!C11),"",VLOOKUP(Requerimiento_Det!C11,Tabla3[#All],2,FALSE)) -> 10000000 | D11: =IF(LEN(Requerimiento_Det!D11)>0,Requerimiento_Det!D11,"") | E11: =IF(ISBLANK(Requerimiento_Det!E11),"",VLOOKUP(Requerimiento_Det!E11,Tabla13[#All],2,FALSE)) -> 0 | F11: =IF(ISBLANK(Requerimiento_Det!F11),"",VLOOKUP(Requerimiento_Det!F11,Tabla12[#All],2,FALSE)) -> 2806 | G11: =IF(ISBLANK(Requerimiento_Det!G11),"",VLOOKUP(Requerimiento_Det!G11,Tabla14[#All],2,FALSE)) -> UNI | H11: =IF(LEN(Requerimiento_Det!H11)>0,Requerimiento_Det!H11,"") -> Mórrope 287276 TRUJILLO PIURA TRUJILLO | I11: =IF(ISBLANK(Requerimiento_Det!I11),"",VLOOKUP(Requerimiento_Det!I11,Tabla5[#All],2,FALSE)) -> C | J11: =IF(LEN(C11)>0,"N","") -> N | K11: =IF(LEN(Requerimiento_Det!J11)>0,Requerimiento_Det!J11,"") -> 1 | L11: =IF(LEN(C11)>0,"0.00","") -> 0.00 | M11: =IF(LEN(C11)>0,"0.00","") -> 0.00 | N11: =IF(LEN(C11)>0,"0.00","") -> 0.00 | O11: =IF(LEN(N11)>0,K11*N11,"") -> 0 | P11: =IF(LEN(C11)>0,"0","") -> 0 | Q11: =IF(LEN(C11)>0,"0","") -> 0 | R11: =IF(LEN(C11)>0,"0.000000","") -> 0.000000 | S11: =IF(LEN(C11)>0,"0.000000","") -> 0.000000 | T11: =IF(LEN(C11)>0,"0","") -> 0 | U11: =IF(LEN(C11)>0,"0","") -> 0 | V11: =IF(LEN(C11)>0,"S","") -> S | W11: =IF(LEN(Requerimiento_Det!L11)>0,Requerimiento_Det!L11,"") -> Mórrope 287276 TRUJILLO PIURA TRUJILLO | X11: =IF(ISBLANK(Requerimiento_Det!M11),"",VLOOKUP(Requerimiento_Det!M11,Tabla8[#All],2,FALSE)) -> 010201 | Y11: =IF(LEN(C11)>0,"PR","") -> PR | Z11: =IF(LEN(C11)>0,"DEMO","") -> DEMO | AA11: =IF(LEN(C11)>0,"N","") -> N | AB11: =IF(LEN(C11)>0,"N","") -> N | AC11: =IF(LEN(C11)>0,"9031501","") -> 9031501 | AD11: =IF(ISBLANK(Requerimiento_Det!N11),"",VLOOKUP(Requerimiento_Det!N11,Tabla1[#All],2,FALSE)) -> 1031100363 | AE11: =IF(ISBLANK(Requerimiento_Det!P11),"",VLOOKUP(Requerimiento_Det!P11,Tabla18[#All],2,FALSE)) -> BTRU
A12: 1 | B12: =IF(LEN(Requerimiento_Det!B12)>0,Requerimiento_Det!B12,"") -> 11 | C12: =IF(ISBLANK(Requerimiento_Det!C12),"",VLOOKUP(Requerimiento_Det!C12,Tabla3[#All],2,FALSE)) -> 10000000 | D12: =IF(LEN(Requerimiento_Det!D12)>0,Requerimiento_Det!D12,"") | E12: =IF(ISBLANK(Requerimiento_Det!E12),"",VLOOKUP(Requerimiento_Det!E12,Tabla13[#All],2,FALSE)) -> 0 | F12: =IF(ISBLANK(Requerimiento_Det!F12),"",VLOOKUP(Requerimiento_Det!F12,Tabla12[#All],2,FALSE)) -> 2806 | G12: =IF(ISBLANK(Requerimiento_Det!G12),"",VLOOKUP(Requerimiento_Det!G12,Tabla14[#All],2,FALSE)) -> UNI | H12: =IF(LEN(Requerimiento_Det!H12)>0,Requerimiento_Det!H12,"") -> Sullana 287585 TALARA PIURA TALARA | I12: =IF(ISBLANK(Requerimiento_Det!I12),"",VLOOKUP(Requerimiento_Det!I12,Tabla5[#All],2,FALSE)) -> C | J12: =IF(LEN(C12)>0,"N","") -> N | K12: =IF(LEN(Requerimiento_Det!J12)>0,Requerimiento_Det!J12,"") -> 1 | L12: =IF(LEN(C12)>0,"0.00","") -> 0.00 | M12: =IF(LEN(C12)>0,"0.00","") -> 0.00 | N12: =IF(LEN(C12)>0,"0.00","") -> 0.00 | O12: =IF(LEN(N12)>0,K12*N12,"") -> 0 | P12: =IF(LEN(C12)>0,"0","") -> 0 | Q12: =IF(LEN(C12)>0,"0","") -> 0 | R12: =IF(LEN(C12)>0,"0.000000","") -> 0.000000 | S12: =IF(LEN(C12)>0,"0.000000","") -> 0.000000 | T12: =IF(LEN(C12)>0,"0","") -> 0 | U12: =IF(LEN(C12)>0,"0","") -> 0 | V12: =IF(LEN(C12)>0,"S","") -> S | W12: =IF(LEN(Requerimiento_Det!L12)>0,Requerimiento_Det!L12,"") -> Sullana 287585 TALARA PIURA TALARA | X12: =IF(ISBLANK(Requerimiento_Det!M12),"",VLOOKUP(Requerimiento_Det!M12,Tabla8[#All],2,FALSE)) -> 010201 | Y12: =IF(LEN(C12)>0,"PR","") -> PR | Z12: =IF(LEN(C12)>0,"DEMO","") -> DEMO | AA12: =IF(LEN(C12)>0,"N","") -> N | AB12: =IF(LEN(C12)>0,"N","") -> N | AC12: =IF(LEN(C12)>0,"9031501","") -> 9031501 | AD12: =IF(ISBLANK(Requerimiento_Det!N12),"",VLOOKUP(Requerimiento_Det!N12,Tabla1[#All],2,FALSE)) -> 1031100278 | AE12: =IF(ISBLANK(Requerimiento_Det!P12),"",VLOOKUP(Requerimiento_Det!P12,Tabla18[#All],2,FALSE)) -> BTRU
A13: 1 | B13: =IF(LEN(Requerimiento_Det!B13)>0,Requerimiento_Det!B13,"") -> 12 | C13: =IF(ISBLANK(Requerimiento_Det!C13),"",VLOOKUP(Requerimiento_Det!C13,Tabla3[#All],2,FALSE)) -> 10000000 | D13: =IF(LEN(Requerimiento_Det!D13)>0,Requerimiento_Det!D13,"") | E13: =IF(ISBLANK(Requerimiento_Det!E13),"",VLOOKUP(Requerimiento_Det!E13,Tabla13[#All],2,FALSE)) -> 0 | F13: =IF(ISBLANK(Requerimiento_Det!F13),"",VLOOKUP(Requerimiento_Det!F13,Tabla12[#All],2,FALSE)) -> 2806 | G13: =IF(ISBLANK(Requerimiento_Det!G13),"",VLOOKUP(Requerimiento_Det!G13,Tabla14[#All],2,FALSE)) -> UNI | H13: =IF(LEN(Requerimiento_Det!H13)>0,Requerimiento_Det!H13,"") -> Pacanguilla 287202 TRUJILLO PIURA TRUJILLO | I13: =IF(ISBLANK(Requerimiento_Det!I13),"",VLOOKUP(Requerimiento_Det!I13,Tabla5[#All],2,FALSE)) -> C | J13: =IF(LEN(C13)>0,"N","") -> N | K13: =IF(LEN(Requerimiento_Det!J13)>0,Requerimiento_Det!J13,"") -> 1 | L13: =IF(LEN(C13)>0,"0.00","") -> 0.00 | M13: =IF(LEN(C13)>0,"0.00","") -> 0.00 | N13: =IF(LEN(C13)>0,"0.00","") -> 0.00 | O13: =IF(LEN(N13)>0,K13*N13,"") -> 0 | P13: =IF(LEN(C13)>0,"0","") -> 0 | Q13: =IF(LEN(C13)>0,"0","") -> 0 | R13: =IF(LEN(C13)>0,"0.000000","") -> 0.000000 | S13: =IF(LEN(C13)>0,"0.000000","") -> 0.000000 | T13: =IF(LEN(C13)>0,"0","") -> 0 | U13: =IF(LEN(C13)>0,"0","") -> 0 | V13: =IF(LEN(C13)>0,"S","") -> S | W13: =IF(LEN(Requerimiento_Det!L13)>0,Requerimiento_Det!L13,"") -> Pacanguilla 287202 TRUJILLO PIURA TRUJILLO | X13: =IF(ISBLANK(Requerimiento_Det!M13),"",VLOOKUP(Requerimiento_Det!M13,Tabla8[#All],2,FALSE)) -> 010201 | Y13: =IF(LEN(C13)>0,"PR","") -> PR | Z13: =IF(LEN(C13)>0,"DEMO","") -> DEMO | AA13: =IF(LEN(C13)>0,"N","") -> N | AB13: =IF(LEN(C13)>0,"N","") -> N | AC13: =IF(LEN(C13)>0,"9031501","") -> 9031501 | AD13: =IF(ISBLANK(Requerimiento_Det!N13),"",VLOOKUP(Requerimiento_Det!N13,Tabla1[#All],2,FALSE)) -> 1031100326 | AE13: =IF(ISBLANK(Requerimiento_Det!P13),"",VLOOKUP(Requerimiento_Det!P13,Tabla18[#All],2,FALSE)) -> BTRU
... A20: 1 | B20: =IF(LEN(Requerimiento_Det!B20)>0,Requerimiento_Det!B20,"") -> 19 | C20: =IF(ISBLANK(Requerimiento_Det!C20),"",VLOOKUP(Requerimiento_Det!C20,Tabla3[#All],2,FALSE)) -> 10000000 | D20: =IF(LEN(Requerimiento_Det!D20)>0,Requerimiento_Det!D20,"") | E20: =IF(ISBLANK(Requerimiento_Det!E20),"",VLOOKUP(Requerimiento_Det!E20,Tabla13[#All],2,FALSE)) -> 0 | F20: =IF(ISBLANK(Requerimiento_Det!F20),"",VLOOKUP(Requerimiento_Det!F20,Tabla12[#All],2,FALSE)) -> 2806 | G20: =IF(ISBLANK(Requerimiento_Det!G20),"",VLOOKUP(Requerimiento_Det!G20,Tabla14[#All],2,FALSE)) -> UNI | H20: =IF(LEN(Requerimiento_Det!H20)>0,Requerimiento_Det!H20,"") -> Sullana 287583 TALARA CHICLAYO TALARA | I20: =IF(ISBLANK(Requerimiento_Det!I20),"",VLOOKUP(Requerimiento_Det!I20,Tabla5[#All],2,FALSE)) -> C | J20: =IF(LEN(C20)>0,"N","") -> N | K20: =IF(LEN(Requerimiento_Det!J20)>0,Requerimiento_Det!J20,"") -> 1 | L20: =IF(LEN(C20)>0,"0.00","") -> 0.00 | M20: =IF(LEN(C20)>0,"0.00","") -> 0.00 | N20: =IF(LEN(C20)>0,"0.00","") -> 0.00 | O20: =IF(LEN(N20)>0,K20*N20,"") -> 0 | P20: =IF(LEN(C20)>0,"0","") -> 0 | Q20: =IF(LEN(C20)>0,"0","") -> 0 | R20: =IF(LEN(C20)>0,"0.000000","") -> 0.000000 | S20: =IF(LEN(C20)>0,"0.000000","") -> 0.000000 | T20: =IF(LEN(C20)>0,"0","") -> 0 | U20: =IF(LEN(C20)>0,"0","") -> 0 | V20: =IF(LEN(C20)>0,"S","") -> S | W20: =IF(LEN(Requerimiento_Det!L20)>0,Requerimiento_Det!L20,"") -> Sullana 287583 TALARA CHICLAYO TALARA | X20: =IF(ISBLANK(Requerimiento_Det!M20),"",VLOOKUP(Requerimiento_Det!M20,Tabla8[#All],2,FALSE)) -> 010201 | Y20: =IF(LEN(C20)>0,"PR","") -> PR | Z20: =IF(LEN(C20)>0,"DEMO","") -> DEMO | AA20: =IF(LEN(C20)>0,"N","") -> N | AB20: =IF(LEN(C20)>0,"N","") -> N | AC20: =IF(LEN(C20)>0,"9031501","") -> 9031501 | AD20: =IF(ISBLANK(Requerimiento_Det!N20),"",VLOOKUP(Requerimiento_Det!N20,Tabla1[#All],2,FALSE)) -> 1031100295 | AE20: =IF(ISBLANK(Requerimiento_Det!P20),"",VLOOKUP(Requerimiento_Det!P20,Tabla18[#All],2,FALSE)) -> BTRU
A21: =IF(LEN(Requerimiento_Det!A21)>0,Requerimiento_Det!A21,"") -> 1 | B21: =IF(LEN(Requerimiento_Det!B21)>0,Requerimiento_Det!B21,"") -> 20 | C21: =IF(ISBLANK(Requerimiento_Det!C21),"",VLOOKUP(Requerimiento_Det!C21,Tabla3[#All],2,FALSE)) -> 10000000 | D21: =IF(LEN(Requerimiento_Det!D21)>0,Requerimiento_Det!D21,"") | E21: =IF(ISBLANK(Requerimiento_Det!E21),"",VLOOKUP(Requerimiento_Det!E21,Tabla13[#All],2,FALSE)) -> 0 | F21: =IF(ISBLANK(Requerimiento_Det!F21),"",VLOOKUP(Requerimiento_Det!F21,Tabla12[#All],2,FALSE)) -> 2806 | G21: =IF(ISBLANK(Requerimiento_Det!G21),"",VLOOKUP(Requerimiento_Det!G21,Tabla14[#All],2,FALSE)) -> UNI | H21: =IF(LEN(Requerimiento_Det!H21)>0,Requerimiento_Det!H21,"") -> Pacanguilla 287206 TRUJILLO PIURA TRUJILLO | I21: =IF(ISBLANK(Requerimiento_Det!I21),"",VLOOKUP(Requerimiento_Det!I21,Tabla5[#All],2,FALSE)) -> C | J21: =IF(LEN(C21)>0,"N","") -> N | K21: =IF(LEN(Requerimiento_Det!J21)>0,Requerimiento_Det!J21,"") -> 1 | L21: =IF(LEN(C21)>0,"0.00","") -> 0.00 | M21: =IF(LEN(C21)>0,"0.00","") -> 0.00 | N21: =IF(LEN(C21)>0,"0.00","") -> 0.00 | O21: =IF(LEN(N21)>0,K21*N21,"") -> 0 | P21: =IF(LEN(C21)>0,"0","") -> 0 | Q21: =IF(LEN(C21)>0,"0","") -> 0 | R21: =IF(LEN(C21)>0,"0.000000","") -> 0.000000 | S21: =IF(LEN(C21)>0,"0.000000","") -> 0.000000 | T21: =IF(LEN(C21)>0,"0","") -> 0 | U21: =IF(LEN(C21)>0,"0","") -> 0 | V21: =IF(LEN(C21)>0,"S","") -> S | W21: =IF(LEN(Requerimiento_Det!L21)>0,Requerimiento_Det!L21,"") -> Pacanguilla 287206 TRUJILLO PIURA TRUJILLO | X21: =IF(ISBLANK(Requerimiento_Det!M21),"",VLOOKUP(Requerimiento_Det!M21,Tabla8[#All],2,FALSE)) -> 010201 | Y21: =IF(LEN(C21)>0,"PR","") -> PR | Z21: =IF(LEN(C21)>0,"DEMO","") -> DEMO | AA21: =IF(LEN(C21)>0,"N","") -> N | AB21: =IF(LEN(C21)>0,"N","") -> N | AC21: =IF(LEN(C21)>0,"9031501","") -> 9031501 | AD21: =IF(ISBLANK(Requerimiento_Det!N21),"",VLOOKUP(Requerimiento_Det!N21,Tabla1[#All],2,FALSE)) -> 1031100337 | AE21: =IF(ISBLANK(Requerimiento_Det!P21),"",VLOOKUP(Requerimiento_Det!P21,Tabla18[#All],2,FALSE)) -> BTRU
A22: =IF(LEN(Requerimiento_Det!A22)>0,Requerimiento_Det!A22,"") -> 1 | B22: =IF(LEN(Requerimiento_Det!B22)>0,Requerimiento_Det!B22,"") -> 21 | C22: =IF(ISBLANK(Requerimiento_Det!C22),"",VLOOKUP(Requerimiento_Det!C22,Tabla3[#All],2,FALSE)) -> 10000000 | D22: =IF(LEN(Requerimiento_Det!D22)>0,Requerimiento_Det!D22,"") | E22: =IF(ISBLANK(Requerimiento_Det!E22),"",VLOOKUP(Requerimiento_Det!E22,Tabla13[#All],2,FALSE)) -> 0 | F22: =IF(ISBLANK(Requerimiento_Det!F22),"",VLOOKUP(Requerimiento_Det!F22,Tabla12[#All],2,FALSE)) -> 2806 | G22: =IF(ISBLANK(Requerimiento_Det!G22),"",VLOOKUP(Requerimiento_Det!G22,Tabla14[#All],2,FALSE)) -> UNI | H22: =IF(LEN(Requerimiento_Det!H22)>0,Requerimiento_Det!H22,"") -> Bayóvar 287032 PUCUSANA PIURA | I22: =IF(ISBLANK(Requerimiento_Det!I22),"",VLOOKUP(Requerimiento_Det!I22,Tabla5[#All],2,FALSE)) -> C | J22: =IF(LEN(C22)>0,"N","") -> N | K22: =IF(LEN(Requerimiento_Det!J22)>0,Requerimiento_Det!J22,"") -> 1 | L22: =IF(LEN(C22)>0,"0.00","") -> 0.00 | M22: =IF(LEN(C22)>0,"0.00","") -> 0.00 | N22: =IF(LEN(C22)>0,"0.00","") -> 0.00 | O22: =IF(LEN(N22)>0,K22*N22,"") -> 0 | P22: =IF(LEN(C22)>0,"0","") -> 0 | Q22: =IF(LEN(C22)>0,"0","") -> 0 | R22: =IF(LEN(C22)>0,"0.000000","") -> 0.000000 | S22: =IF(LEN(C22)>0,"0.000000","") -> 0.000000 | T22: =IF(LEN(C22)>0,"0","") -> 0 | U22: =IF(LEN(C22)>0,"0","") -> 0 | V22: =IF(LEN(C22)>0,"S","") -> S | W22: =IF(LEN(Requerimiento_Det!L22)>0,Requerimiento_Det!L22,"") -> Bayóvar 287032 PUCUSANA PIURA | X22: =IF(ISBLANK(Requerimiento_Det!M22),"",VLOOKUP(Requerimiento_Det!M22,Tabla8[#All],2,FALSE)) -> 010201 | Y22: =IF(LEN(C22)>0,"PR","") -> PR | Z22: =IF(LEN(C22)>0,"DEMO","") -> DEMO | AA22: =IF(LEN(C22)>0,"N","") -> N | AB22: =IF(LEN(C22)>0,"N","") -> N | AC22: =IF(LEN(C22)>0,"9031501","") -> 9031501 | AD22: =IF(ISBLANK(Requerimiento_Det!N22),"",VLOOKUP(Requerimiento_Det!N22,Tabla1[#All],2,FALSE)) -> 1031100332 | AE22: =IF(ISBLANK(Requerimiento_Det!P22),"",VLOOKUP(Requerimiento_Det!P22,Tabla18[#All],2,FALSE)) -> BTRU
A23: =IF(LEN(Requerimiento_Det!A23)>0,Requerimiento_Det!A23,"") -> 1 | B23: =IF(LEN(Requerimiento_Det!B23)>0,Requerimiento_Det!B23,"") -> 22 | C23: =IF(ISBLANK(Requerimiento_Det!C23),"",VLOOKUP(Requerimiento_Det!C23,Tabla3[#All],2,FALSE)) -> 10000000 | D23: =IF(LEN(Requerimiento_Det!D23)>0,Requerimiento_Det!D23,"") | E23: =IF(ISBLANK(Requerimiento_Det!E23),"",VLOOKUP(Requerimiento_Det!E23,Tabla13[#All],2,FALSE)) -> 0 | F23: =IF(ISBLANK(Requerimiento_Det!F23),"",VLOOKUP(Requerimiento_Det!F23,Tabla12[#All],2,FALSE)) -> 2806 | G23: =IF(ISBLANK(Requerimiento_Det!G23),"",VLOOKUP(Requerimiento_Det!G23,Tabla14[#All],2,FALSE)) -> UNI | H23: =IF(LEN(Requerimiento_Det!H23)>0,Requerimiento_Det!H23,"") -> Pacanguilla 287275 TRUJILLO PIURA TRUJILLO | I23: =IF(ISBLANK(Requerimiento_Det!I23),"",VLOOKUP(Requerimiento_Det!I23,Tabla5[#All],2,FALSE)) -> C | J23: =IF(LEN(C23)>0,"N","") -> N | K23: =IF(LEN(Requerimiento_Det!J23)>0,Requerimiento_Det!J23,"") -> 1 | L23: =IF(LEN(C23)>0,"0.00","") -> 0.00 | M23: =IF(LEN(C23)>0,"0.00","") -> 0.00 | N23: =IF(LEN(C23)>0,"0.00","") -> 0.00 | O23: =IF(LEN(N23)>0,K23*N23,"") -> 0 | P23: =IF(LEN(C23)>0,"0","") -> 0 | Q23: =IF(LEN(C23)>0,"0","") -> 0 | R23: =IF(LEN(C23)>0,"0.000000","") -> 0.000000 | S23: =IF(LEN(C23)>0,"0.000000","") -> 0.000000 | T23: =IF(LEN(C23)>0,"0","") -> 0 | U23: =IF(LEN(C23)>0,"0","") -> 0 | V23: =IF(LEN(C23)>0,"S","") -> S | W23: =IF(LEN(Requerimiento_Det!L23)>0,Requerimiento_Det!L23,"") -> Pacanguilla 287275 TRUJILLO PIURA TRUJILLO | X23: =IF(ISBLANK(Requerimiento_Det!M23),"",VLOOKUP(Requerimiento_Det!M23,Tabla8[#All],2,FALSE)) -> 010201 | Y23: =IF(LEN(C23)>0,"PR","") -> PR | Z23: =IF(LEN(C23)>0,"DEMO","") -> DEMO | AA23: =IF(LEN(C23)>0,"N","") -> N | AB23: =IF(LEN(C23)>0,"N","") -> N | AC23: =IF(LEN(C23)>0,"9031501","") -> 9031501 | AD23: =IF(ISBLANK(Requerimiento_Det!N23),"",VLOOKUP(Requerimiento_Det!N23,Tabla1[#All],2,FALSE)) -> 1031100362 | AE23: =IF(ISBLANK(Requerimiento_Det!P23),"",VLOOKUP(Requerimiento_Det!P23,Tabla18[#All],2,FALSE)) -> BTRU
A24: =IF(LEN(Requerimiento_Det!A24)>0,Requerimiento_Det!A24,"") -> 1 | B24: =IF(LEN(Requerimiento_Det!B24)>0,Requerimiento_Det!B24,"") -> 23 | C24: =IF(ISBLANK(Requerimiento_Det!C24),"",VLOOKUP(Requerimiento_Det!C24,Tabla3[#All],2,FALSE)) -> 10000000 | D24: =IF(LEN(Requerimiento_Det!D24)>0,Requerimiento_Det!D24,"") | E24: =IF(ISBLANK(Requerimiento_Det!E24),"",VLOOKUP(Requerimiento_Det!E24,Tabla13[#All],2,FALSE)) -> 0 | F24: =IF(ISBLANK(Requerimiento_Det!F24),"",VLOOKUP(Requerimiento_Det!F24,Tabla12[#All],2,FALSE)) -> 2806 | G24: =IF(ISBLANK(Requerimiento_Det!G24),"",VLOOKUP(Requerimiento_Det!G24,Tabla14[#All],2,FALSE)) -> UNI | H24: =IF(LEN(Requerimiento_Det!H24)>0,Requerimiento_Det!H24,"") -> Pacanguilla 287278 TRUJILLO PIURA TRUJILLO | I24: =IF(ISBLANK(Requerimiento_Det!I24),"",VLOOKUP(Requerimiento_Det!I24,Tabla5[#All],2,FALSE)) -> C | J24: =IF(LEN(C24)>0,"N","") -> N | K24: =IF(LEN(Requerimiento_Det!J24)>0,Requerimiento_Det!J24,"") -> 1 | L24: =IF(LEN(C24)>0,"0.00","") -> 0.00 | M24: =IF(LEN(C24)>0,"0.00","") -> 0.00 | N24: =IF(LEN(C24)>0,"0.00","") -> 0.00 | O24: =IF(LEN(N24)>0,K24*N24,"") -> 0 | P24: =IF(LEN(C24)>0,"0","") -> 0 | Q24: =IF(LEN(C24)>0,"0","") -> 0 | R24: =IF(LEN(C24)>0,"0.000000","") -> 0.000000 | S24: =IF(LEN(C24)>0,"0.000000","") -> 0.000000 | T24: =IF(LEN(C24)>0,"0","") -> 0 | U24: =IF(LEN(C24)>0,"0","") -> 0 | V24: =IF(LEN(C24)>0,"S","") -> S | W24: =IF(LEN(Requerimiento_Det!L24)>0,Requerimiento_Det!L24,"") -> Pacanguilla 287278 TRUJILLO PIURA TRUJILLO | X24: =IF(ISBLANK(Requerimiento_Det!M24),"",VLOOKUP(Requerimiento_Det!M24,Tabla8[#All],2,FALSE)) -> 010201 | Y24: =IF(LEN(C24)>0,"PR","") -> PR | Z24: =IF(LEN(C24)>0,"DEMO","") -> DEMO | AA24: =IF(LEN(C24)>0,"N","") -> N | AB24: =IF(LEN(C24)>0,"N","") -> N | AC24: =IF(LEN(C24)>0,"9031501","") -> 9031501 | AD24: =IF(ISBLANK(Requerimiento_Det!N24),"",VLOOKUP(Requerimiento_Det!N24,Tabla1[#All],2,FALSE)) -> 1031100238 | AE24: =IF(ISBLANK(Requerimiento_Det!P24),"",VLOOKUP(Requerimiento_Det!P24,Tabla18[#All],2,FALSE)) -> BTRU
A25: =IF(LEN(Requerimiento_Det!A25)>0,Requerimiento_Det!A25,"") -> 1 | B25: =IF(LEN(Requerimiento_Det!B25)>0,Requerimiento_Det!B25,"") -> 24 | C25: =IF(ISBLANK(Requerimiento_Det!C25),"",VLOOKUP(Requerimiento_Det!C25,Tabla3[#All],2,FALSE)) -> 10000000 | D25: =IF(LEN(Requerimiento_Det!D25)>0,Requerimiento_Det!D25,"") | E25: =IF(ISBLANK(Requerimiento_Det!E25),"",VLOOKUP(Requerimiento_Det!E25,Tabla13[#All],2,FALSE)) -> 0 | F25: =IF(ISBLANK(Requerimiento_Det!F25),"",VLOOKUP(Requerimiento_Det!F25,Tabla12[#All],2,FALSE)) -> 2806 | G25: =IF(ISBLANK(Requerimiento_Det!G25),"",VLOOKUP(Requerimiento_Det!G25,Tabla14[#All],2,FALSE)) -> UNI | H25: =IF(LEN(Requerimiento_Det!H25)>0,Requerimiento_Det!H25,"") -> Pacanguilla 287207 TRUJILLO PIURA TRUJILLO | I25: =IF(ISBLANK(Requerimiento_Det!I25),"",VLOOKUP(Requerimiento_Det!I25,Tabla5[#All],2,FALSE)) -> C | J25: =IF(LEN(C25)>0,"N","") -> N | K25: =IF(LEN(Requerimiento_Det!J25)>0,Requerimiento_Det!J25,"") -> 1 | L25: =IF(LEN(C25)>0,"0.00","") -> 0.00 | M25: =IF(LEN(C25)>0,"0.00","") -> 0.00 | N25: =IF(LEN(C25)>0,"0.00","") -> 0.00 | O25: =IF(LEN(N25)>0,K25*N25,"") -> 0 | P25: =IF(LEN(C25)>0,"0","") -> 0 | Q25: =IF(LEN(C25)>0,"0","") -> 0 | R25: =IF(LEN(C25)>0,"0.000000","") -> 0.000000 | S25: =IF(LEN(C25)>0,"0.000000","") -> 0.000000 | T25: =IF(LEN(C25)>0,"0","") -> 0 | U25: =IF(LEN(C25)>0,"0","") -> 0 | V25: =IF(LEN(C25)>0,"S","") -> S | W25: =IF(LEN(Requerimiento_Det!L25)>0,Requerimiento_Det!L25,"") -> Pacanguilla 287207 TRUJILLO PIURA TRUJILLO | X25: =IF(ISBLANK(Requerimiento_Det!M25),"",VLOOKUP(Requerimiento_Det!M25,Tabla8[#All],2,FALSE)) -> 010201 | Y25: =IF(LEN(C25)>0,"PR","") -> PR | Z25: =IF(LEN(C25)>0,"DEMO","") -> DEMO | AA25: =IF(LEN(C25)>0,"N","") -> N | AB25: =IF(LEN(C25)>0,"N","") -> N | AC25: =IF(LEN(C25)>0,"9031501","") -> 9031501 | AD25: =IF(ISBLANK(Requerimiento_Det!N25),"",VLOOKUP(Requerimiento_Det!N25,Tabla1[#All],2,FALSE)) -> 1031100357 | AE25: =IF(ISBLANK(Requerimiento_Det!P25),"",VLOOKUP(Requerimiento_Det!P25,Tabla18[#All],2,FALSE)) -> BTRU
A26: =IF(LEN(Requerimiento_Det!A26)>0,Requerimiento_Det!A26,"") -> 1 | B26: =IF(LEN(Requerimiento_Det!B26)>0,Requerimiento_Det!B26,"") -> 25 | C26: =IF(ISBLANK(Requerimiento_Det!C26),"",VLOOKUP(Requerimiento_Det!C26,Tabla3[#All],2,FALSE)) -> 10000000 | D26: =IF(LEN(Requerimiento_Det!D26)>0,Requerimiento_Det!D26,"") | E26: =IF(ISBLANK(Requerimiento_Det!E26),"",VLOOKUP(Requerimiento_Det!E26,Tabla13[#All],2,FALSE)) -> 0 | F26: =IF(ISBLANK(Requerimiento_Det!F26),"",VLOOKUP(Requerimiento_Det!F26,Tabla12[#All],2,FALSE)) -> 2806 | G26: =IF(ISBLANK(Requerimiento_Det!G26),"",VLOOKUP(Requerimiento_Det!G26,Tabla14[#All],2,FALSE)) -> UNI | H26: =IF(LEN(Requerimiento_Det!H26)>0,Requerimiento_Det!H26,"") -> Bayóvar 287037 PUCUSANA PIURA | I26: =IF(ISBLANK(Requerimiento_Det!I26),"",VLOOKUP(Requerimiento_Det!I26,Tabla5[#All],2,FALSE)) -> C | J26: =IF(LEN(C26)>0,"N","") -> N | K26: =IF(LEN(Requerimiento_Det!J26)>0,Requerimiento_Det!J26,"") -> 1 | L26: =IF(LEN(C26)>0,"0.00","") -> 0.00 | M26: =IF(LEN(C26)>0,"0.00","") -> 0.00 | N26: =IF(LEN(C26)>0,"0.00","") -> 0.00 | O26: =IF(LEN(N26)>0,K26*N26,"") -> 0 | P26: =IF(LEN(C26)>0,"0","") -> 0 | Q26: =IF(LEN(C26)>0,"0","") -> 0 | R26: =IF(LEN(C26)>0,"0.000000","") -> 0.000000 | S26: =IF(LEN(C26)>0,"0.000000","") -> 0.000000 | T26: =IF(LEN(C26)>0,"0","") -> 0 | U26: =IF(LEN(C26)>0,"0","") -> 0 | V26: =IF(LEN(C26)>0,"S","") -> S | W26: =IF(LEN(Requerimiento_Det!L26)>0,Requerimiento_Det!L26,"") -> Bayóvar 287037 PUCUSANA PIURA | X26: =IF(ISBLANK(Requerimiento_Det!M26),"",VLOOKUP(Requerimiento_Det!M26,Tabla8[#All],2,FALSE)) -> 010201 | Y26: =IF(LEN(C26)>0,"PR","") -> PR | Z26: =IF(LEN(C26)>0,"DEMO","") -> DEMO | AA26: =IF(LEN(C26)>0,"N","") -> N | AB26: =IF(LEN(C26)>0,"N","") -> N | AC26: =IF(LEN(C26)>0,"9031501","") -> 9031501 | AD26: =IF(ISBLANK(Requerimiento_Det!N26),"",VLOOKUP(Requerimiento_Det!N26,Tabla1[#All],2,FALSE)) -> 1031100315 | AE26: =IF(ISBLANK(Requerimiento_Det!P26),"",VLOOKUP(Requerimiento_Det!P26,Tabla18[#All],2,FALSE)) -> BTRU
A27: =IF(LEN(Requerimiento_Det!A27)>0,Requerimiento_Det!A27,"") -> 1 | B27: =IF(LEN(Requerimiento_Det!B27)>0,Requerimiento_Det!B27,"") -> 26 | C27: =IF(ISBLANK(Requerimiento_Det!C27),"",VLOOKUP(Requerimiento_Det!C27,Tabla3[#All],2,FALSE)) -> 10000000 | D27: =IF(LEN(Requerimiento_Det!D27)>0,Requerimiento_Det!D27,"") | E27: =IF(ISBLANK(Requerimiento_Det!E27),"",VLOOKUP(Requerimiento_Det!E27,Tabla13[#All],2,FALSE)) -> 0 | F27: =IF(ISBLANK(Requerimiento_Det!F27),"",VLOOKUP(Requerimiento_Det!F27,Tabla12[#All],2,FALSE)) -> 2806 | G27: =IF(ISBLANK(Requerimiento_Det!G27),"",VLOOKUP(Requerimiento_Det!G27,Tabla14[#All],2,FALSE)) -> UNI | H27: =IF(LEN(Requerimiento_Det!H27)>0,Requerimiento_Det!H27,"") -> Chicama 287213 TRUJILLO PIURA TRUJILLO | I27: =IF(ISBLANK(Requerimiento_Det!I27),"",VLOOKUP(Requerimiento_Det!I27,Tabla5[#All],2,FALSE)) -> C | J27: =IF(LEN(C27)>0,"N","") -> N | K27: =IF(LEN(Requerimiento_Det!J27)>0,Requerimiento_Det!J27,"") -> 1 | L27: =IF(LEN(C27)>0,"0.00","") -> 0.00 | M27: =IF(LEN(C27)>0,"0.00","") -> 0.00 | N27: =IF(LEN(C27)>0,"0.00","") -> 0.00 | O27: =IF(LEN(N27)>0,K27*N27,"") -> 0 | P27: =IF(LEN(C27)>0,"0","") -> 0 | Q27: =IF(LEN(C27)>0,"0","") -> 0 | R27: =IF(LEN(C27)>0,"0.000000","") -> 0.000000 | S27: =IF(LEN(C27)>0,"0.000000","") -> 0.000000 | T27: =IF(LEN(C27)>0,"0","") -> 0 | U27: =IF(LEN(C27)>0,"0","") -> 0 | V27: =IF(LEN(C27)>0,"S","") -> S | W27: =IF(LEN(Requerimiento_Det!L27)>0,Requerimiento_Det!L27,"") -> Chicama 287213 TRUJILLO PIURA TRUJILLO | X27: =IF(ISBLANK(Requerimiento_Det!M27),"",VLOOKUP(Requerimiento_Det!M27,Tabla8[#All],2,FALSE)) -> 010201 | Y27: =IF(LEN(C27)>0,"PR","") -> PR | Z27: =IF(LEN(C27)>0,"DEMO","") -> DEMO | AA27: =IF(LEN(C27)>0,"N","") -> N | AB27: =IF(LEN(C27)>0,"N","") -> N | AC27: =IF(LEN(C27)>0,"9031501","") -> 9031501 | AD27: =IF(ISBLANK(Requerimiento_Det!N27),"",VLOOKUP(Requerimiento_Det!N27,Tabla1[#All],2,FALSE)) -> 1031100265 | AE27: =IF(ISBLANK(Requerimiento_Det!P27),"",VLOOKUP(Requerimiento_Det!P27,Tabla18[#All],2,FALSE)) -> BTRU
A28: =IF(LEN(Requerimiento_Det!A28)>0,Requerimiento_Det!A28,"") -> 1 | B28: =IF(LEN(Requerimiento_Det!B28)>0,Requerimiento_Det!B28,"") -> 27 | C28: =IF(ISBLANK(Requerimiento_Det!C28),"",VLOOKUP(Requerimiento_Det!C28,Tabla3[#All],2,FALSE)) -> 10000000 | D28: =IF(LEN(Requerimiento_Det!D28)>0,Requerimiento_Det!D28,"") | E28: =IF(ISBLANK(Requerimiento_Det!E28),"",VLOOKUP(Requerimiento_Det!E28,Tabla13[#All],2,FALSE)) -> 0 | F28: =IF(ISBLANK(Requerimiento_Det!F28),"",VLOOKUP(Requerimiento_Det!F28,Tabla12[#All],2,FALSE)) -> 2806 | G28: =IF(ISBLANK(Requerimiento_Det!G28),"",VLOOKUP(Requerimiento_Det!G28,Tabla14[#All],2,FALSE)) -> UNI | H28: =IF(LEN(Requerimiento_Det!H28)>0,Requerimiento_Det!H28,"") -> Chicama 287176 TRUJILLO PIURA TRUJILLO | I28: =IF(ISBLANK(Requerimiento_Det!I28),"",VLOOKUP(Requerimiento_Det!I28,Tabla5[#All],2,FALSE)) -> C | J28: =IF(LEN(C28)>0,"N","") -> N | K28: =IF(LEN(Requerimiento_Det!J28)>0,Requerimiento_Det!J28,"") -> 1 | L28: =IF(LEN(C28)>0,"0.00","") -> 0.00 | M28: =IF(LEN(C28)>0,"0.00","") -> 0.00 | N28: =IF(LEN(C28)>0,"0.00","") -> 0.00 | O28: =IF(LEN(N28)>0,K28*N28,"") -> 0 | P28: =IF(LEN(C28)>0,"0","") -> 0 | Q28: =IF(LEN(C28)>0,"0","") -> 0 | R28: =IF(LEN(C28)>0,"0.000000","") -> 0.000000 | S28: =IF(LEN(C28)>0,"0.000000","") -> 0.000000 | T28: =IF(LEN(C28)>0,"0","") -> 0 | U28: =IF(LEN(C28)>0,"0","") -> 0 | V28: =IF(LEN(C28)>0,"S","") -> S | W28: =IF(LEN(Requerimiento_Det!L28)>0,Requerimiento_Det!L28,"") -> Chicama 287176 TRUJILLO PIURA TRUJILLO | X28: =IF(ISBLANK(Requerimiento_Det!M28),"",VLOOKUP(Requerimiento_Det!M28,Tabla8[#All],2,FALSE)) -> 010201 | Y28: =IF(LEN(C28)>0,"PR","") -> PR | Z28: =IF(LEN(C28)>0,"DEMO","") -> DEMO | AA28: =IF(LEN(C28)>0,"N","") -> N | AB28: =IF(LEN(C28)>0,"N","") -> N | AC28: =IF(LEN(C28)>0,"9031501","") -> 9031501 | AD28: =IF(ISBLANK(Requerimiento_Det!N28),"",VLOOKUP(Requerimiento_Det!N28,Tabla1[#All],2,FALSE)) -> 1031100242 | AE28: =IF(ISBLANK(Requerimiento_Det!P28),"",VLOOKUP(Requerimiento_Det!P28,Tabla18[#All],2,FALSE)) -> BTRU
A29: =IF(LEN(Requerimiento_Det!A29)>0,Requerimiento_Det!A29,"") -> 1 | B29: =IF(LEN(Requerimiento_Det!B29)>0,Requerimiento_Det!B29,"") -> 28 | C29: =IF(ISBLANK(Requerimiento_Det!C29),"",VLOOKUP(Requerimiento_Det!C29,Tabla3[#All],2,FALSE)) -> 10000000 | D29: =IF(LEN(Requerimiento_Det!D29)>0,Requerimiento_Det!D29,"") | E29: =IF(ISBLANK(Requerimiento_Det!E29),"",VLOOKUP(Requerimiento_Det!E29,Tabla13[#All],2,FALSE)) -> 0 | F29: =IF(ISBLANK(Requerimiento_Det!F29),"",VLOOKUP(Requerimiento_Det!F29,Tabla12[#All],2,FALSE)) -> 2806 | G29: =IF(ISBLANK(Requerimiento_Det!G29),"",VLOOKUP(Requerimiento_Det!G29,Tabla14[#All],2,FALSE)) -> UNI | H29: =IF(LEN(Requerimiento_Det!H29)>0,Requerimiento_Det!H29,"") -> Pacanguilla 286734 TRUJILLO TUMBES TRUJILLO | I29: =IF(ISBLANK(Requerimiento_Det!I29),"",VLOOKUP(Requerimiento_Det!I29,Tabla5[#All],2,FALSE)) -> C | J29: =IF(LEN(C29)>0,"N","") -> N | K29: =IF(LEN(Requerimiento_Det!J29)>0,Requerimiento_Det!J29,"") -> 1 | L29: =IF(LEN(C29)>0,"0.00","") -> 0.00 | M29: =IF(LEN(C29)>0,"0.00","") -> 0.00 | N29: =IF(LEN(C29)>0,"0.00","") -> 0.00 | O29: =IF(LEN(N29)>0,K29*N29,"") -> 0 | P29: =IF(LEN(C29)>0,"0","") -> 0 | Q29: =IF(LEN(C29)>0,"0","") -> 0 | R29: =IF(LEN(C29)>0,"0.000000","") -> 0.000000 | S29: =IF(LEN(C29)>0,"0.000000","") -> 0.000000 | T29: =IF(LEN(C29)>0,"0","") -> 0 | U29: =IF(LEN(C29)>0,"0","") -> 0 | V29: =IF(LEN(C29)>0,"S","") -> S | W29: =IF(LEN(Requerimiento_Det!L29)>0,Requerimiento_Det!L29,"") -> Pacanguilla 286734 TRUJILLO TUMBES TRUJILLO | X29: =IF(ISBLANK(Requerimiento_Det!M29),"",VLOOKUP(Requerimiento_Det!M29,Tabla8[#All],2,FALSE)) -> 010201 | Y29: =IF(LEN(C29)>0,"PR","") -> PR | Z29: =IF(LEN(C29)>0,"DEMO","") -> DEMO | AA29: =IF(LEN(C29)>0,"N","") -> N | AB29: =IF(LEN(C29)>0,"N","") -> N | AC29: =IF(LEN(C29)>0,"9031501","") -> 9031501 | AD29: =IF(ISBLANK(Requerimiento_Det!N29),"",VLOOKUP(Requerimiento_Det!N29,Tabla1[#All],2,FALSE)) -> 1031100328 | AE29: =IF(ISBLANK(Requerimiento_Det!P29),"",VLOOKUP(Requerimiento_Det!P29,Tabla18[#All],2,FALSE)) -> BTRU
A30: =IF(LEN(Requerimiento_Det!A30)>0,Requerimiento_Det!A30,"") -> 1 | B30: =IF(LEN(Requerimiento_Det!B30)>0,Requerimiento_Det!B30,"") -> 29 | C30: =IF(ISBLANK(Requerimiento_Det!C30),"",VLOOKUP(Requerimiento_Det!C30,Tabla3[#All],2,FALSE)) -> 10000000 | D30: =IF(LEN(Requerimiento_Det!D30)>0,Requerimiento_Det!D30,"") | E30: =IF(ISBLANK(Requerimiento_Det!E30),"",VLOOKUP(Requerimiento_Det!E30,Tabla13[#All],2,FALSE)) -> 0 | F30: =IF(ISBLANK(Requerimiento_Det!F30),"",VLOOKUP(Requerimiento_Det!F30,Tabla12[#All],2,FALSE)) -> 2806 | G30: =IF(ISBLANK(Requerimiento_Det!G30),"",VLOOKUP(Requerimiento_Det!G30,Tabla14[#All],2,FALSE)) -> UNI | H30: =IF(LEN(Requerimiento_Det!H30)>0,Requerimiento_Det!H30,"") -> Chicama 287195 TRUJILLO PACASMAYO TRUJILLO | I30: =IF(ISBLANK(Requerimiento_Det!I30),"",VLOOKUP(Requerimiento_Det!I30,Tabla5[#All],2,FALSE)) -> C | J30: =IF(LEN(C30)>0,"N","") -> N | K30: =IF(LEN(Requerimiento_Det!J30)>0,Requerimiento_Det!J30,"") -> 1 | L30: =IF(LEN(C30)>0,"0.00","") -> 0.00 | M30: =IF(LEN(C30)>0,"0.00","") -> 0.00 | N30: =IF(LEN(C30)>0,"0.00","") -> 0.00 | O30: =IF(LEN(N30)>0,K30*N30,"") -> 0 | P30: =IF(LEN(C30)>0,"0","") -> 0 | Q30: =IF(LEN(C30)>0,"0","") -> 0 | R30: =IF(LEN(C30)>0,"0.000000","") -> 0.000000 | S30: =IF(LEN(C30)>0,"0.000000","") -> 0.000000 | T30: =IF(LEN(C30)>0,"0","") -> 0 | U30: =IF(LEN(C30)>0,"0","") -> 0 | V30: =IF(LEN(C30)>0,"S","") -> S | W30: =IF(LEN(Requerimiento_Det!L30)>0,Requerimiento_Det!L30,"") -> Chicama 287195 TRUJILLO PACASMAYO TRUJILLO | X30: =IF(ISBLANK(Requerimiento_Det!M30),"",VLOOKUP(Requerimiento_Det!M30,Tabla8[#All],2,FALSE)) -> 010201 | Y30: =IF(LEN(C30)>0,"PR","") -> PR | Z30: =IF(LEN(C30)>0,"DEMO","") -> DEMO | AA30: =IF(LEN(C30)>0,"N","") -> N | AB30: =IF(LEN(C30)>0,"N","") -> N | AC30: =IF(LEN(C30)>0,"9031501","") -> 9031501 | AD30: =IF(ISBLANK(Requerimiento_Det!N30),"",VLOOKUP(Requerimiento_Det!N30,Tabla1[#All],2,FALSE)) -> 1031100358 | AE30: =IF(ISBLANK(Requerimiento_Det!P30),"",VLOOKUP(Requerimiento_Det!P30,Tabla18[#All],2,FALSE)) -> BTRU
A31: =IF(LEN(Requerimiento_Det!A31)>0,Requerimiento_Det!A31,"") -> 1 | B31: =IF(LEN(Requerimiento_Det!B31)>0,Requerimiento_Det!B31,"") -> 30 | C31: =IF(ISBLANK(Requerimiento_Det!C31),"",VLOOKUP(Requerimiento_Det!C31,Tabla3[#All],2,FALSE)) -> 10000000 | D31: =IF(LEN(Requerimiento_Det!D31)>0,Requerimiento_Det!D31,"") | E31: =IF(ISBLANK(Requerimiento_Det!E31),"",VLOOKUP(Requerimiento_Det!E31,Tabla13[#All],2,FALSE)) -> 0 | F31: =IF(ISBLANK(Requerimiento_Det!F31),"",VLOOKUP(Requerimiento_Det!F31,Tabla12[#All],2,FALSE)) -> 2806 | G31: =IF(ISBLANK(Requerimiento_Det!G31),"",VLOOKUP(Requerimiento_Det!G31,Tabla14[#All],2,FALSE)) -> UNI | H31: =IF(LEN(Requerimiento_Det!H31)>0,Requerimiento_Det!H31,"") -> Pacanguilla 287270 TRUJILLO CHICLAYO TRUJILLO | I31: =IF(ISBLANK(Requerimiento_Det!I31),"",VLOOKUP(Requerimiento_Det!I31,Tabla5[#All],2,FALSE)) -> C | J31: =IF(LEN(C31)>0,"N","") -> N | K31: =IF(LEN(Requerimiento_Det!J31)>0,Requerimiento_Det!J31,"") -> 1 | L31: =IF(LEN(C31)>0,"0.00","") -> 0.00 | M31: =IF(LEN(C31)>0,"0.00","") -> 0.00 | N31: =IF(LEN(C31)>0,"0.00","") -> 0.00 | O31: =IF(LEN(N31)>0,K31*N31,"") -> 0 | P31: =IF(LEN(C31)>0,"0","") -> 0 | Q31: =IF(LEN(C31)>0,"0","") -> 0 | R31: =IF(LEN(C31)>0,"0.000000","") -> 0.000000 | S31: =IF(LEN(C31)>0,"0.000000","") -> 0.000000 | T31: =IF(LEN(C31)>0,"0","") -> 0 | U31: =IF(LEN(C31)>0,"0","") -> 0 | V31: =IF(LEN(C31)>0,"S","") -> S | W31: =IF(LEN(Requerimiento_Det!L31)>0,Requerimiento_Det!L31,"") -> Pacanguilla 287270 TRUJILLO CHICLAYO TRUJILLO | X31: =IF(ISBLANK(Requerimiento_Det!M31),"",VLOOKUP(Requerimiento_Det!M31,Tabla8[#All],2,FALSE)) -> 010201 | Y31: =IF(LEN(C31)>0,"PR","") -> PR | Z31: =IF(LEN(C31)>0,"DEMO","") -> DEMO | AA31: =IF(LEN(C31)>0,"N","") -> N | AB31: =IF(LEN(C31)>0,"N","") -> N | AC31: =IF(LEN(C31)>0,"9031501","") -> 9031501 | AD31: =IF(ISBLANK(Requerimiento_Det!N31),"",VLOOKUP(Requerimiento_Det!N31,Tabla1[#All],2,FALSE)) -> 1031100257 | AE31: =IF(ISBLANK(Requerimiento_Det!P31),"",VLOOKUP(Requerimiento_Det!P31,Tabla18[#All],2,FALSE)) -> BTRU
A32: =IF(LEN(Requerimiento_Det!A32)>0,Requerimiento_Det!A32,"") -> 1 | B32: =IF(LEN(Requerimiento_Det!B32)>0,Requerimiento_Det!B32,"") -> 31 | C32: =IF(ISBLANK(Requerimiento_Det!C32),"",VLOOKUP(Requerimiento_Det!C32,Tabla3[#All],2,FALSE)) -> 10000000 | D32: =IF(LEN(Requerimiento_Det!D32)>0,Requerimiento_Det!D32,"") | E32: =IF(ISBLANK(Requerimiento_Det!E32),"",VLOOKUP(Requerimiento_Det!E32,Tabla13[#All],2,FALSE)) -> 0 | F32: =IF(ISBLANK(Requerimiento_Det!F32),"",VLOOKUP(Requerimiento_Det!F32,Tabla12[#All],2,FALSE)) -> 2806 | G32: =IF(ISBLANK(Requerimiento_Det!G32),"",VLOOKUP(Requerimiento_Det!G32,Tabla14[#All],2,FALSE)) -> UNI | H32: =IF(LEN(Requerimiento_Det!H32)>0,Requerimiento_Det!H32,"") -> Pacanguilla 287267 TRUJILLO CHICLAYO TRUJILLO | I32: =IF(ISBLANK(Requerimiento_Det!I32),"",VLOOKUP(Requerimiento_Det!I32,Tabla5[#All],2,FALSE)) -> C | J32: =IF(LEN(C32)>0,"N","") -> N | K32: =IF(LEN(Requerimiento_Det!J32)>0,Requerimiento_Det!J32,"") -> 1 | L32: =IF(LEN(C32)>0,"0.00","") -> 0.00 | M32: =IF(LEN(C32)>0,"0.00","") -> 0.00 | N32: =IF(LEN(C32)>0,"0.00","") -> 0.00 | O32: =IF(LEN(N32)>0,K32*N32,"") -> 0 | P32: =IF(LEN(C32)>0,"0","") -> 0 | Q32: =IF(LEN(C32)>0,"0","") -> 0 | R32: =IF(LEN(C32)>0,"0.000000","") -> 0.000000 | S32: =IF(LEN(C32)>0,"0.000000","") -> 0.000000 | T32: =IF(LEN(C32)>0,"0","") -> 0 | U32: =IF(LEN(C32)>0,"0","") -> 0 | V32: =IF(LEN(C32)>0,"S","") -> S | W32: =IF(LEN(Requerimiento_Det!L32)>0,Requerimiento_Det!L32,"") -> Pacanguilla 287267 TRUJILLO CHICLAYO TRUJILLO | X32: =IF(ISBLANK(Requerimiento_Det!M32),"",VLOOKUP(Requerimiento_Det!M32,Tabla8[#All],2,FALSE)) -> 010201 | Y32: =IF(LEN(C32)>0,"PR","") -> PR | Z32: =IF(LEN(C32)>0,"DEMO","") -> DEMO | AA32: =IF(LEN(C32)>0,"N","") -> N | AB32: =IF(LEN(C32)>0,"N","") -> N | AC32: =IF(LEN(C32)>0,"9031501","") -> 9031501 | AD32: =IF(ISBLANK(Requerimiento_Det!N32),"",VLOOKUP(Requerimiento_Det!N32,Tabla1[#All],2,FALSE)) -> 1031100339 | AE32: =IF(ISBLANK(Requerimiento_Det!P32),"",VLOOKUP(Requerimiento_Det!P32,Tabla18[#All],2,FALSE)) -> BTRU
... A800: =IF(LEN(Requerimiento_Det!A800)>0,Requerimiento_Det!A800,"") | B800: =IF(LEN(Requerimiento_Det!B800)>0,Requerimiento_Det!B800,"") | C800: =IF(ISBLANK(Requerimiento_Det!C800),"",VLOOKUP(Requerimiento_Det!C800,Tabla3[#All],2,FALSE)) | D800: =IF(LEN(Requerimiento_Det!D800)>0,Requerimiento_Det!D800,"") | E800: =IF(ISBLANK(Requerimiento_Det!E800),"",VLOOKUP(Requerimiento_Det!E800,Tabla13[#All],2,FALSE)) | F800: =IF(ISBLANK(Requerimiento_Det!F800),"",VLOOKUP(Requerimiento_Det!F800,Tabla12[#All],2,FALSE)) | G800: =IF(ISBLANK(Requerimiento_Det!G800),"",VLOOKUP(Requerimiento_Det!G800,Tabla14[#All],2,FALSE)) | H800: =IF(LEN(Requerimiento_Det!H800)>0,Requerimiento_Det!H800,"") | I800: =IF(ISBLANK(Requerimiento_Det!I800),"",VLOOKUP(Requerimiento_Det!I800,Tabla5[#All],2,FALSE)) | J800: =IF(LEN(C800)>0,"N","") | K800: =IF(LEN(Requerimiento_Det!J800)>0,Requerimiento_Det!J800,"") | L800: =IF(LEN(C800)>0,"0.00","") | M800: =IF(LEN(C800)>0,"0.00","") | N800: =IF(LEN(C800)>0,"0.00","") | O800: =IF(LEN(N800)>0,K800*N800,"") | P800: =IF(LEN(C800)>0,"0","") | Q800: =IF(LEN(C800)>0,"0","") | R800: =IF(LEN(C800)>0,"0.000000","") | S800: =IF(LEN(C800)>0,"0.000000","") | T800: =IF(LEN(C800)>0,"0","") | U800: =IF(LEN(C800)>0,"0","") | V800: =IF(LEN(C800)>0,"S","") | W800: =IF(LEN(Requerimiento_Det!L800)>0,Requerimiento_Det!L800,"") | X800: =IF(ISBLANK(Requerimiento_Det!M800),"",VLOOKUP(Requerimiento_Det!M800,Tabla8[#All],2,FALSE)) | Y800: =IF(LEN(C800)>0,"PR","") | Z800: =IF(LEN(C800)>0,"DEMO","") | AA800: =IF(LEN(C800)>0,"N","") | AB800: =IF(LEN(C800)>0,"N","") | AC800: =IF(LEN(C800)>0,"9031501","") | AD800: =IF(ISBLANK(Requerimiento_Det!N800),"",VLOOKUP(Requerimiento_Det!N800,Tabla1[#All],2,FALSE)) | AE800: =IF(ISBLANK(Requerimiento_Det!P800),"",VLOOKUP(Requerimiento_Det!P800,Tabla18[#All],2,FALSE))

Sheet Cotizar
A1: SecuenciaCabecera | B1: SecuenciaDetalle | C1: CompaniaSocio | D1: Placa | E1: Proyecto | F1: FormaDePago | G1: DocumentoFiscal | H1: Cantidad | I1: PrecioUnitarioconIGV | J1: Observaciones
A2: =IF(LEN(Requerimiento_Det!A2)>0,Requerimiento_Det!A2,"") -> 1 | B2: =(IF(LEN(C2)>0,ROW(B2)-1,"")) -> 1 | C2: GRUPO TRANSPESA SAC | D2: TBH880 | E2: =IF(ISBLANK(Cotizar!D2),"",VLOOKUP(Cotizar!D2,Tabla1[#All],2,FALSE)) -> 1031100355 | F2: Contado | G2: 20522547957 | H2: 1 | I2: 88.4002 | J2: Transpesa 1
A3: 1 | B3: =(IF(LEN(C3)>0,ROW(B3)-1,"")) -> 2 | C3: GRUPO TRANSPESA SAC | D3: T8H891 | E3: =IF(ISBLANK(Cotizar!D3),"",VLOOKUP(Cotizar!D3,Tabla1[#All],2,FALSE)) -> 1031100265 | F3: Contado | G3: 20522547957 | H3: 1 | I3: 88.4002 | J3: Transpesa 2
A4: 1 | B4: =(IF(LEN(C4)>0,ROW(B4)-1,"")) -> 3 | C4: GRUPO TRANSPESA SAC | D4: TBB913 | E4: =IF(ISBLANK(Cotizar!D4),"",VLOOKUP(Cotizar!D4,Tabla1[#All],2,FALSE)) -> 1031100349 | F4: Contado | G4: 20522547957 | H4: 1 | I4: 88.4002 | J4: Transpesa 3
A5: 1 | B5: =(IF(LEN(C5)>0,ROW(B5)-1,"")) -> 4 | C5: GRUPO TRANSPESA SAC | D5: T8B945 | E5: =IF(ISBLANK(Cotizar!D5),"",VLOOKUP(Cotizar!D5,Tabla1[#All],2,FALSE)) -> 1031100256 | F5: Contado | G5: 20522547957 | H5: 1 | I5: 88.4002 | J5: Transpesa 4
A6: 1 | B6: =(IF(LEN(C6)>0,ROW(B6)-1,"")) -> 5 | C6: GRUPO TRANSPESA SAC | D6: T8Z852 | E6: =IF(ISBLANK(Cotizar!D6),"",VLOOKUP(Cotizar!D6,Tabla1[#All],2,FALSE)) -> 1031100294 | F6: Contado | G6: 20522547957 | H6: 1 | I6: 88.4002 | J6: Transpesa 5
A7: 1 | B7: =(IF(LEN(C7)>0,ROW(B7)-1,"")) -> 6 | C7: GRUPO TRANSPESA SAC | D7: TBH915 | E7: =IF(ISBLANK(Cotizar!D7),"",VLOOKUP(Cotizar!D7,Tabla1[#All],2,FALSE)) -> 1031100361 | F7: Contado | G7: 20522547957 | H7: 1 | I7: 88.4002 | J7: Transpesa 6
A8: 1 | B8: =(IF(LEN(C8)>0,ROW(B8)-1,"")) -> 7 | C8: GRUPO TRANSPESA SAC | D8: T7F876 | E8: =IF(ISBLANK(Cotizar!D8),"",VLOOKUP(Cotizar!D8,Tabla1[#All],2,FALSE)) -> 1031100248 | F8: Contado | G8: 20522547957 | H8: 1 | I8: 88.4002 | J8: Transpesa 7
A9: 1 | B9: =(IF(LEN(C9)>0,ROW(B9)-1,"")) -> 8 | C9: GRUPO TRANSPESA SAC | D9: T8Z872 | E9: =IF(ISBLANK(Cotizar!D9),"",VLOOKUP(Cotizar!D9,Tabla1[#All],2,FALSE)) -> 1031100289 | F9: Contado | G9: 20522547957 | H9: 1 | I9: 88.4002 | J9: Transpesa 8
A10: 1 | B10: =(IF(LEN(C10)>0,ROW(B10)-1,"")) -> 9 | C10: GRUPO TRANSPESA SAC | D10: TAD876 | E10: =IF(ISBLANK(Cotizar!D10),"",VLOOKUP(Cotizar!D10,Tabla1[#All],2,FALSE)) -> 1031100329 | F10: Contado | G10: 20522547957 | H10: 1 | I10: 88.4002 | J10: Transpesa 9
A11: 1 | B11: =(IF(LEN(C11)>0,ROW(B11)-1,"")) -> 10 | C11: GRUPO TRANSPESA SAC | D11: T4T909 | E11: =IF(ISBLANK(Cotizar!D11),"",VLOOKUP(Cotizar!D11,Tabla1[#All],2,FALSE)) -> 1031100116 | F11: Contado | G11: 20522547957 | H11: 1 | I11: 88.4002 | J11: Transpesa 10
A12: 1 | B12: =(IF(LEN(C12)>0,ROW(B12)-1,"")) -> 11 | C12: GRUPO TRANSPESA SAC | D12: TBH895 | E12: =IF(ISBLANK(Cotizar!D12),"",VLOOKUP(Cotizar!D12,Tabla1[#All],2,FALSE)) -> 1031100358 | F12: Contado | G12: 20522547957 | H12: 1 | I12: 88.4002 | J12: Transpesa 11
A13: 1 | B13: =(IF(LEN(C13)>0,ROW(B13)-1,"")) -> 12 | C13: GRUPO TRANSPESA SAC | D13: TAD887 | E13: =IF(ISBLANK(Cotizar!D13),"",VLOOKUP(Cotizar!D13,Tabla1[#All],2,FALSE)) -> 1031100327 | F13: Contado | G13: 20522547957 | H13: 1 | I13: 88.4002 | J13: Transpesa 12
A14: 1 | B14: =(IF(LEN(C14)>0,ROW(B14)-1,"")) -> 13 | C14: GRUPO TRANSPESA SAC | D14: T7F853 | E14: =IF(ISBLANK(Cotizar!D14),"",VLOOKUP(Cotizar!D14,Tabla1[#All],2,FALSE)) -> 1031100239 | F14: Contado | G14: 20522547957 | H14: 1 | I14: 88.4002 | J14: Transpesa 13
... A20: 1 | B20: =(IF(LEN(C20)>0,ROW(B20)-1,"")) -> 19 | C20: GRUPO TRANSPESA SAC | D20: T9G939 | E20: =IF(ISBLANK(Cotizar!D20),"",VLOOKUP(Cotizar!D20,Tabla1[#All],2,FALSE)) -> 1031100319 | F20: Contado | G20: 20522547957 | H20: 1 | I20: 88.4002 | J20: Transpesa 19
A21: =IF(LEN(Requerimiento_Det!A21)>0,Requerimiento_Det!A21,"") -> 1 | B21: =(IF(LEN(C21)>0,ROW(B21)-1,"")) -> 20 | C21: GRUPO TRANSPESA SAC | D21: TBB913 | E21: =IF(ISBLANK(Cotizar!D21),"",VLOOKUP(Cotizar!D21,Tabla1[#All],2,FALSE)) -> 1031100349 | F21: Contado | G21: 20522547957 | H21: 1 | I21: 88.4002 | J21: Transpesa 20
A22: =IF(LEN(Requerimiento_Det!A22)>0,Requerimiento_Det!A22,"") -> 1 | B22: =(IF(LEN(C22)>0,ROW(B22)-1,"")) -> 21 | C22: GRUPO TRANSPESA SAC | D22: T8H889 | E22: =IF(ISBLANK(Cotizar!D22),"",VLOOKUP(Cotizar!D22,Tabla1[#All],2,FALSE)) -> 1031100267 | F22: Contado | G22: 20522547957 | H22: 1 | I22: 88.4002 | J22: Transpesa 21
A23: =IF(LEN(Requerimiento_Det!A23)>0,Requerimiento_Det!A23,"") -> 1 | B23: =(IF(LEN(C23)>0,ROW(B23)-1,"")) -> 22 | C23: GRUPO TRANSPESA SAC | D23: T8Z858 | E23: =IF(ISBLANK(Cotizar!D23),"",VLOOKUP(Cotizar!D23,Tabla1[#All],2,FALSE)) -> 1031100287 | F23: Contado | G23: 20522547957 | H23: 1 | I23: 88.4002 | J23: Transpesa 22
A24: =IF(LEN(Requerimiento_Det!A24)>0,Requerimiento_Det!A24,"") -> 1 | B24: =(IF(LEN(C24)>0,ROW(B24)-1,"")) -> 23 | C24: GRUPO TRANSPESA SAC | D24: T3M854 | E24: =IF(ISBLANK(Cotizar!D24),"",VLOOKUP(Cotizar!D24,Tabla1[#All],2,FALSE)) -> 1031100087 | F24: Contado | G24: 20522547957 | H24: 1 | I24: 58.0999 | J24: Transpesa 23
A25: =IF(LEN(Requerimiento_Det!A25)>0,Requerimiento_Det!A25,"") -> 1 | B25: =(IF(LEN(C25)>0,ROW(B25)-1,"")) -> 24 | C25: GRUPO TRANSPESA SAC | D25: T9P803 | E25: =IF(ISBLANK(Cotizar!D25),"",VLOOKUP(Cotizar!D25,Tabla1[#All],2,FALSE)) -> 1031100311 | F25: Contado | G25: 20522547957 | H25: 1 | I25: 58.0999 | J25: Transpesa 24
A26: =IF(LEN(Requerimiento_Det!A26)>0,Requerimiento_Det!A26,"") -> 1 | B26: =(IF(LEN(C26)>0,ROW(B26)-1,"")) -> 25 | C26: GRUPO TRANSPESA SAC | D26: T9R862 | E26: =IF(ISBLANK(Cotizar!D26),"",VLOOKUP(Cotizar!D26,Tabla1[#All],2,FALSE)) -> 1031100314 | F26: Contado | G26: 20522547957 | H26: 1 | I26: 58.0999 | J26: Transpesa 25
A27: =IF(LEN(Requerimiento_Det!A27)>0,Requerimiento_Det!A27,"") -> 1 | B27: =(IF(LEN(C27)>0,ROW(B27)-1,"")) -> 26 | C27: GRUPO TRANSPESA SAC | D27: T9G847 | E27: =IF(ISBLANK(Cotizar!D27),"",VLOOKUP(Cotizar!D27,Tabla1[#All],2,FALSE)) -> 1031100305 | F27: Contado | G27: 20522547957 | H27: 1 | I27: 58.0999 | J27: Transpesa 26
A28: =IF(LEN(Requerimiento_Det!A28)>0,Requerimiento_Det!A28,"") -> 1 | B28: =(IF(LEN(C28)>0,ROW(B28)-1,"")) -> 27 | C28: GRUPO TRANSPESA SAC | D28: TBH919 | E28: =IF(ISBLANK(Cotizar!D28),"",VLOOKUP(Cotizar!D28,Tabla1[#All],2,FALSE)) -> 1031100363 | F28: Contado | G28: 20522547957 | H28: 1 | I28: 58.0999 | J28: Transpesa 27
A29: =IF(LEN(Requerimiento_Det!A29)>0,Requerimiento_Det!A29,"") -> 1 | B29: =(IF(LEN(C29)>0,ROW(B29)-1,"")) -> 28 | C29: GRUPO TRANSPESA SAC | D29: T7F876 | E29: =IF(ISBLANK(Cotizar!D29),"",VLOOKUP(Cotizar!D29,Tabla1[#All],2,FALSE)) -> 1031100248 | F29: Contado | G29: 20522547957 | H29: 1 | I29: 58.0999 | J29: Transpesa 28
A30: =IF(LEN(Requerimiento_Det!A30)>0,Requerimiento_Det!A30,"") -> 1 | B30: =(IF(LEN(C30)>0,ROW(B30)-1,"")) -> 29 | C30: GRUPO TRANSPESA SAC | D30: T9O939 | E30: =IF(ISBLANK(Cotizar!D30),"",VLOOKUP(Cotizar!D30,Tabla1[#All],2,FALSE)) -> 1031100309 | F30: Contado | G30: 20522547957 | H30: 1 | I30: 58.0999 | J30: Transpesa 29
A31: =IF(LEN(Requerimiento_Det!A31)>0,Requerimiento_Det!A31,"") -> 1 | B31: =(IF(LEN(C31)>0,ROW(B31)-1,"")) -> 30 | C31: GRUPO TRANSPESA SAC | D31: T9G838 | E31: =IF(ISBLANK(Cotizar!D31),"",VLOOKUP(Cotizar!D31,Tabla1[#All],2,FALSE)) -> 1031100336 | F31: Contado | G31: 20522547957 | H31: 1 | I31: 58.0999 | J31: Transpesa 30
A32: =IF(LEN(Requerimiento_Det!A32)>0,Requerimiento_Det!A32,"") -> 1 | B32: =(IF(LEN(C32)>0,ROW(B32)-1,"")) -> 31 | C32: GRUPO TRANSPESA SAC | D32: TBH895 | E32: =IF(ISBLANK(Cotizar!D32),"",VLOOKUP(Cotizar!D32,Tabla1[#All],2,FALSE)) -> 1031100358 | F32: Contado | G32: 20522547957 | H32: 1 | I32: 58.0999 | J32: Transpesa 31
... A309: =IF(LEN(Requerimiento_Det!A309)>0,Requerimiento_Det!A309,"") -> 1 | B309: =(IF(LEN(C309)>0,ROW(B309)-1,"")) -> 308 | C309: GRUPO TRANSPESA SAC | D309: T7F886 | E309: =IF(ISBLANK(Cotizar!D309),"",VLOOKUP(Cotizar!D309,Tabla1[#All],2,FALSE)) -> 1031100251 | F309: Contado | G309: 20522547957 | H309: 1 | I309: 58 | J309: Transpesa 308
A310: =IF(LEN(Requerimiento_Det!A310)>0,Requerimiento_Det!A310,"") -> 1 | B310: =(IF(LEN(C310)>0,ROW(B310)-1,""))
A311: =IF(LEN(Requerimiento_Det!A311)>0,Requerimiento_Det!A311,"") -> 1 | B311: =(IF(LEN(C311)>0,ROW(B311)-1,""))
A312: =IF(LEN(Requerimiento_Det!A312)>0,Requerimiento_Det!A312,"") -> 1 | B312: =(IF(LEN(C312)>0,ROW(B312)-1,""))
A313: =IF(LEN(Requerimiento_Det!A313)>0,Requerimiento_Det!A313,"") -> 1 | B313: =(IF(LEN(C313)>0,ROW(B313)-1,""))
A314: =IF(LEN(Requerimiento_Det!A314)>0,Requerimiento_Det!A314,"") -> 1 | B314: =(IF(LEN(C314)>0,ROW(B314)-1,""))
A315: =IF(LEN(Requerimiento_Det!A315)>0,Requerimiento_Det!A315,"") -> 1 | B315: =(IF(LEN(C315)>0,ROW(B315)-1,""))
A316: =IF(LEN(Requerimiento_Det!A316)>0,Requerimiento_Det!A316,"") -> 1 | B316: =(IF(LEN(C316)>0,ROW(B316)-1,""))
A317: =IF(LEN(Requerimiento_Det!A317)>0,Requerimiento_Det!A317,"") -> 1 | B317: =(IF(LEN(C317)>0,ROW(B317)-1,""))
A318: =IF(LEN(Requerimiento_Det!A318)>0,Requerimiento_Det!A318,"") -> 1 | B318: =(IF(LEN(C318)>0,ROW(B318)-1,""))
A319: =IF(LEN(Requerimiento_Det!A319)>0,Requerimiento_Det!A319,"") -> 1 | B319: =(IF(LEN(C319)>0,ROW(B319)-1,""))
A320: =IF(LEN(Requerimiento_Det!A320)>0,Requerimiento_Det!A320,"") -> 1 | B320: =(IF(LEN(C320)>0,ROW(B320)-1,""))
A321: =IF(LEN(Requerimiento_Det!A321)>0,Requerimiento_Det!A321,"") -> 1 | B321: =(IF(LEN(C321)>0,ROW(B321)-1,""))
... A1000: =IF(LEN(Requerimiento_Det!A1000)>0,Requerimiento_Det!A1000,"") | B1000: =(IF(LEN(C1000)>0,ROW(B1000)-1,""))

Sheet GenerarDataCotizar
A1: CompaniaSocio | B1: SecuenciaCabecera | C1: CotizacionSecuencia | D1: Afe | E1: FormadePago | F1: DocumentoFiscal | G1: Cantidad | H1: PrecioUnitarioconIGV | I1: Observaciones
A2: =IF(ISBLANK(Cotizar!C2),"",VLOOKUP(Cotizar!C2,Tabla3[#All],2,FALSE)) -> 10000000 | B2: =IF(LEN(Cotizar!A2)>0,Cotizar!A2,"") -> 1 | C2: =IF(LEN(Cotizar!B2)>0,Cotizar!B2,"") -> 1 | D2: =IF(ISBLANK(Cotizar!D2),"",VLOOKUP(Cotizar!D2,Tabla1[#All],2,FALSE)) -> 1031100355 | E2: =IF(ISBLANK(Cotizar!F2),"",VLOOKUP(Cotizar!F2,Tabla11[#All],2,FALSE)) -> 001 | F2: =IF(LEN(Cotizar!G2)>0,Cotizar!G2,"") -> 20522547957 | G2: =IF(LEN(Cotizar!H2)>0,Cotizar!H2,"") -> 1 | H2: =IF(LEN(Cotizar!I2)>0,Cotizar!I2,"") -> 88.4002 | I2: =IF(LEN(Cotizar!J2)>0,Cotizar!J2,"") -> Transpesa 1
A3: =IF(ISBLANK(Cotizar!C3),"",VLOOKUP(Cotizar!C3,Tabla3[#All],2,FALSE)) -> 10000000 | B3: =IF(LEN(Cotizar!A3)>0,Cotizar!A3,"") -> 1 | C3: =IF(LEN(Cotizar!B3)>0,Cotizar!B3,"") -> 2 | D3: =IF(ISBLANK(Cotizar!D3),"",VLOOKUP(Cotizar!D3,Tabla1[#All],2,FALSE)) -> 1031100265 | E3: =IF(ISBLANK(Cotizar!F3),"",VLOOKUP(Cotizar!F3,Tabla11[#All],2,FALSE)) -> 001 | F3: =IF(LEN(Cotizar!G3)>0,Cotizar!G3,"") -> 20522547957 | G3: =IF(LEN(Cotizar!H3)>0,Cotizar!H3,"") -> 1 | H3: =IF(LEN(Cotizar!I3)>0,Cotizar!I3,"") -> 88.4002 | I3: =IF(LEN(Cotizar!J3)>0,Cotizar!J3,"") -> Transpesa 2
A4: =IF(ISBLANK(Cotizar!C4),"",VLOOKUP(Cotizar!C4,Tabla3[#All],2,FALSE)) -> 10000000 | B4: =IF(LEN(Cotizar!A4)>0,Cotizar!A4,"") -> 1 | C4: =IF(LEN(Cotizar!B4)>0,Cotizar!B4,"") -> 3 | D4: =IF(ISBLANK(Cotizar!D4),"",VLOOKUP(Cotizar!D4,Tabla1[#All],2,FALSE)) -> 1031100349 | E4: =IF(ISBLANK(Cotizar!F4),"",VLOOKUP(Cotizar!F4,Tabla11[#All],2,FALSE)) -> 001 | F4: =IF(LEN(Cotizar!G4)>0,Cotizar!G4,"") -> 20522547957 | G4: =IF(LEN(Cotizar!H4)>0,Cotizar!H4,"") -> 1 | H4: =IF(LEN(Cotizar!I4)>0,Cotizar!I4,"") -> 88.4002 | I4: =IF(LEN(Cotizar!J4)>0,Cotizar!J4,"") -> Transpesa 3
A5: =IF(ISBLANK(Cotizar!C5),"",VLOOKUP(Cotizar!C5,Tabla3[#All],2,FALSE)) -> 10000000 | B5: =IF(LEN(Cotizar!A5)>0,Cotizar!A5,"") -> 1 | C5: =IF(LEN(Cotizar!B5)>0,Cotizar!B5,"") -> 4 | D5: =IF(ISBLANK(Cotizar!D5),"",VLOOKUP(Cotizar!D5,Tabla1[#All],2,FALSE)) -> 1031100256 | E5: =IF(ISBLANK(Cotizar!F5),"",VLOOKUP(Cotizar!F5,Tabla11[#All],2,FALSE)) -> 001 | F5: =IF(LEN(Cotizar!G5)>0,Cotizar!G5,"") -> 20522547957 | G5: =IF(LEN(Cotizar!H5)>0,Cotizar!H5,"") -> 1 | H5: =IF(LEN(Cotizar!I5)>0,Cotizar!I5,"") -> 88.4002 | I5: =IF(LEN(Cotizar!J5)>0,Cotizar!J5,"") -> Transpesa 4
A6: =IF(ISBLANK(Cotizar!C6),"",VLOOKUP(Cotizar!C6,Tabla3[#All],2,FALSE)) -> 10000000 | B6: =IF(LEN(Cotizar!A6)>0,Cotizar!A6,"") -> 1 | C6: =IF(LEN(Cotizar!B6)>0,Cotizar!B6,"") -> 5 | D6: =IF(ISBLANK(Cotizar!D6),"",VLOOKUP(Cotizar!D6,Tabla1[#All],2,FALSE)) -> 1031100294 | E6: =IF(ISBLANK(Cotizar!F6),"",VLOOKUP(Cotizar!F6,Tabla11[#All],2,FALSE)) -> 001 | F6: =IF(LEN(Cotizar!G6)>0,Cotizar!G6,"") -> 20522547957 | G6: =IF(LEN(Cotizar!H6)>0,Cotizar!H6,"") -> 1 | H6: =IF(LEN(Cotizar!I6)>0,Cotizar!I6,"") -> 88.4002 | I6: =IF(LEN(Cotizar!J6)>0,Cotizar!J6,"") -> Transpesa 5
A7: =IF(ISBLANK(Cotizar!C7),"",VLOOKUP(Cotizar!C7,Tabla3[#All],2,FALSE)) -> 10000000 | B7: =IF(LEN(Cotizar!A7)>0,Cotizar!A7,"") -> 1 | C7: =IF(LEN(Cotizar!B7)>0,Cotizar!B7,"") -> 6 | D7: =IF(ISBLANK(Cotizar!D7),"",VLOOKUP(Cotizar!D7,Tabla1[#All],2,FALSE)) -> 1031100361 | E7: =IF(ISBLANK(Cotizar!F7),"",VLOOKUP(Cotizar!F7,Tabla11[#All],2,FALSE)) -> 001 | F7: =IF(LEN(Cotizar!G7)>0,Cotizar!G7,"") -> 20522547957 | G7: =IF(LEN(Cotizar!H7)>0,Cotizar!H7,"") -> 1 | H7: =IF(LEN(Cotizar!I7)>0,Cotizar!I7,"") -> 88.4002 | I7: =IF(LEN(Cotizar!J7)>0,Cotizar!J7,"") -> Transpesa 6
A8: =IF(ISBLANK(Cotizar!C8),"",VLOOKUP(Cotizar!C8,Tabla3[#All],2,FALSE)) -> 10000000 | B8: =IF(LEN(Cotizar!A8)>0,Cotizar!A8,"") -> 1 | C8: =IF(LEN(Cotizar!B8)>0,Cotizar!B8,"") -> 7 | D8: =IF(ISBLANK(Cotizar!D8),"",VLOOKUP(Cotizar!D8,Tabla1[#All],2,FALSE)) -> 1031100248 | E8: =IF(ISBLANK(Cotizar!F8),"",VLOOKUP(Cotizar!F8,Tabla11[#All],2,FALSE)) -> 001 | F8: =IF(LEN(Cotizar!G8)>0,Cotizar!G8,"") -> 20522547957 | G8: =IF(LEN(Cotizar!H8)>0,Cotizar!H8,"") -> 1 | H8: =IF(LEN(Cotizar!I8)>0,Cotizar!I8,"") -> 88.4002 | I8: =IF(LEN(Cotizar!J8)>0,Cotizar!J8,"") -> Transpesa 7
A9: =IF(ISBLANK(Cotizar!C9),"",VLOOKUP(Cotizar!C9,Tabla3[#All],2,FALSE)) -> 10000000 | B9: =IF(LEN(Cotizar!A9)>0,Cotizar!A9,"") -> 1 | C9: =IF(LEN(Cotizar!B9)>0,Cotizar!B9,"") -> 8 | D9: =IF(ISBLANK(Cotizar!D9),"",VLOOKUP(Cotizar!D9,Tabla1[#All],2,FALSE)) -> 1031100289 | E9: =IF(ISBLANK(Cotizar!F9),"",VLOOKUP(Cotizar!F9,Tabla11[#All],2,FALSE)) -> 001 | F9: =IF(LEN(Cotizar!G9)>0,Cotizar!G9,"") -> 20522547957 | G9: =IF(LEN(Cotizar!H9)>0,Cotizar!H9,"") -> 1 | H9: =IF(LEN(Cotizar!I9)>0,Cotizar!I9,"") -> 88.4002 | I9: =IF(LEN(Cotizar!J9)>0,Cotizar!J9,"") -> Transpesa 8
A10: =IF(ISBLANK(Cotizar!C10),"",VLOOKUP(Cotizar!C10,Tabla3[#All],2,FALSE)) -> 10000000 | B10: =IF(LEN(Cotizar!A10)>0,Cotizar!A10,"") -> 1 | C10: =IF(LEN(Cotizar!B10)>0,Cotizar!B10,"") -> 9 | D10: =IF(ISBLANK(Cotizar!D10),"",VLOOKUP(Cotizar!D10,Tabla1[#All],2,FALSE)) -> 1031100329 | E10: =IF(ISBLANK(Cotizar!F10),"",VLOOKUP(Cotizar!F10,Tabla11[#All],2,FALSE)) -> 001 | F10: =IF(LEN(Cotizar!G10)>0,Cotizar!G10,"") -> 20522547957 | G10: =IF(LEN(Cotizar!H10)>0,Cotizar!H10,"") -> 1 | H10: =IF(LEN(Cotizar!I10)>0,Cotizar!I10,"") -> 88.4002 | I10: =IF(LEN(Cotizar!J10)>0,Cotizar!J10,"") -> Transpesa 9
A11: =IF(ISBLANK(Cotizar!C11),"",VLOOKUP(Cotizar!C11,Tabla3[#All],2,FALSE)) -> 10000000 | B11: =IF(LEN(Cotizar!A11)>0,Cotizar!A11,"") -> 1 | C11: =IF(LEN(Cotizar!B11)>0,Cotizar!B11,"") -> 10 | D11: =IF(ISBLANK(Cotizar!D11),"",VLOOKUP(Cotizar!D11,Tabla1[#All],2,FALSE)) -> 1031100116 | E11: =IF(ISBLANK(Cotizar!F11),"",VLOOKUP(Cotizar!F11,Tabla11[#All],2,FALSE)) -> 001 | F11: =IF(LEN(Cotizar!G11)>0,Cotizar!G11,"") -> 20522547957 | G11: =IF(LEN(Cotizar!H11)>0,Cotizar!H11,"") -> 1 | H11: =IF(LEN(Cotizar!I11)>0,Cotizar!I11,"") -> 88.4002 | I11: =IF(LEN(Cotizar!J11)>0,Cotizar!J11,"") -> Transpesa 10
A12: =IF(ISBLANK(Cotizar!C12),"",VLOOKUP(Cotizar!C12,Tabla3[#All],2,FALSE)) -> 10000000 | B12: =IF(LEN(Cotizar!A12)>0,Cotizar!A12,"") -> 1 | C12: =IF(LEN(Cotizar!B12)>0,Cotizar!B12,"") -> 11 | D12: =IF(ISBLANK(Cotizar!D12),"",VLOOKUP(Cotizar!D12,Tabla1[#All],2,FALSE)) -> 1031100358 | E12: =IF(ISBLANK(Cotizar!F12),"",VLOOKUP(Cotizar!F12,Tabla11[#All],2,FALSE)) -> 001 | F12: =IF(LEN(Cotizar!G12)>0,Cotizar!G12,"") -> 20522547957 | G12: =IF(LEN(Cotizar!H12)>0,Cotizar!H12,"") -> 1 | H12: =IF(LEN(Cotizar!I12)>0,Cotizar!I12,"") -> 88.4002 | I12: =IF(LEN(Cotizar!J12)>0,Cotizar!J12,"") -> Transpesa 11
A13: =IF(ISBLANK(Cotizar!C13),"",VLOOKUP(Cotizar!C13,Tabla3[#All],2,FALSE)) -> 10000000 | B13: =IF(LEN(Cotizar!A13)>0,Cotizar!A13,"") -> 1 | C13: =IF(LEN(Cotizar!B13)>0,Cotizar!B13,"") -> 12 | D13: =IF(ISBLANK(Cotizar!D13),"",VLOOKUP(Cotizar!D13,Tabla1[#All],2,FALSE)) -> 1031100327 | E13: =IF(ISBLANK(Cotizar!F13),"",VLOOKUP(Cotizar!F13,Tabla11[#All],2,FALSE)) -> 001 | F13: =IF(LEN(Cotizar!G13)>0,Cotizar!G13,"") -> 20522547957 | G13: =IF(LEN(Cotizar!H13)>0,Cotizar!H13,"") -> 1 | H13: =IF(LEN(Cotizar!I13)>0,Cotizar!I13,"") -> 88.4002 | I13: =IF(LEN(Cotizar!J13)>0,Cotizar!J13,"") -> Transpesa 12
... A800: =IF(ISBLANK(Cotizar!C800),"",VLOOKUP(Cotizar!C800,Tabla3[#All],2,FALSE)) | B800: =IF(LEN(Cotizar!A800)>0,Cotizar!A800,"") | C800: =IF(LEN(Cotizar!B800)>0,Cotizar!B800,"") | D800: =IF(ISBLANK(Cotizar!D800),"",VLOOKUP(Cotizar!D800,Tabla1[#All],2,FALSE)) | E800: =IF(ISBLANK(Cotizar!F800),"",VLOOKUP(Cotizar!F800,Tabla11[#All],2,FALSE)) | F800: =IF(LEN(Cotizar!G800)>0,Cotizar!G800,"") | G800: =IF(LEN(Cotizar!H800)>0,Cotizar!H800,"") | H800: =IF(LEN(Cotizar!I800)>0,Cotizar!I800,"") | I800: =IF(LEN(Cotizar!J800)>0,Cotizar!J800,"")

Sheet Maestro
A1: CompaniaNombre | B1: CompaniaSocio | D1: Descripcion | E1: Clasificacion | G1: Dirigido a | H1: ComprasAlmacenFlag | J1: Item | K1: DescripcionItem | M1: DescripcionLocal | N1: Commodity | P1: DescripcionLocal | Q1: Sucursal
A2: GRUPO TRANSPESA SAC | B2: 10000000 | D2: Activos Menores | E2: ACM | G2: Compras | H2: C | J2: 1203001093 | K2: ACERO 42 CR VCL. 140 RED. 1 | M2: Servicio de Vigilancia | N2: 0701 | P2: Base Trujillo | Q2: BTRU
A3: CONTROL | B3: 20000000 | D3: Activos Mayores | E3: ACT | G3: Almacen | H3: A | J3: 1203001087 | K3: ACERO 42 CR VCL. 140 RED. 1-1/4 | M3: Resguardo Policial | N3: 0702 | P3: Base Lima | Q3: Base Lima
A4: TRANSPORTES ADRIEL | B4: 30000000 | D4: Cargo Directo | E4: CDR | J4: 1203001092 | K4: ACERO 42 CR VCL. 140 RED. 1-1/8 | M4: Camionetas | N4: 0801 | P4: Larrea1 | Q4: LAR1
A5: FABRICACIONES BRA S.A.C. | B5: 40000000 | D5: Compra Directa | E5: CMP | G5: NombreDep | H5: Departamento | J5: 1203001086 | K5: ACERO 42 CR VCL. 140 RED. 115 MM. P/ EJE DE CARRETA | M5: Grua | N5: 0802 | P5: Larrea2 | Q5: LAR2
A6: ALMACENES ALTRA SAC | B6: 50000000 | D6: Consignacion | E6: CSG | G6: <Departamento Default> | H6: 999 | J6: 1203001091 | K6: ACERO 42 CR VCL. 140 RED. 1-3/4 | M6: Maquinaria | N6: 0803 | P6: BOCANEGRA | Q6: LIMA
A7: CONSORCIO AEROMARITIMO TRANSP | B7: 60000000 | D7: ENTREGA PARCIAL | E7: EPA | G7: ALMACEN SALAVERRY | H7: SAL | J7: 1203001089 | K7: ACERO 42 CR VCL. 140 RED. 28 MM | M7: Bienes Muebles | N7: 0804 | P7: Servicio de Maquinaria Pesada | Q7: MAQU
A8: AGENCIA DE ADUANA AMT S.A.C. | B8: 70000000 | D8: URGENTE | E8: LOC | G8: ALMACEN Y MAQUINARIA | H8: AYM | J8: 1203001090 | K8: ACERO 42 CR VCL. 140 RED. 60 MM | M8: SERVICIO DE INSTALACIÓN DE RED | N8: 0901 | P8: Almacen Santa catalina | Q8: OTRO
A9: GRUPO DISOR SAC | B9: 80000000 | D9: NORMAL | E9: MAD | G9: AUDITORIA | H9: AUD | J9: 0000005545 | K9: ARRANQUE DIRECTOTRIFASICO 380 DE 3.4 HP CON BOBINA 380 | M9: Mantenimiento de Software | N9: 0902 | P9: Salaverry | Q9: SAL
A10: Almacenes -Transpesa | B10: ALQALM | D10: Obras en Curso | E10: OEC | G10: COMBUSTIBLE | H10: COM | J10: 0000004549 | K10: BASE FILTRO COMBUSTIBLE CEBADOR M2 RK 50401FTL | M10: Mantenimiento de Hardware | N10: 0903 | P10: La Encalada | Q10: ENCA
D11: Producción | E11: PRD | G11: CONTABILIDAD | H11: AC | J11: 0000004867 | K11: BLOQUEADOR DE BATERIA 001559001 HELLA | M11: Requerimientos Inmplementación SPRING | N11: 0904
A12: Proyecto | B12: NumeroPlaca | D12: Req. Automática Stock | E12: RAU | G12: FACTURACION | H12: FAC | J12: 0000005138 | K12: BOMBA DE AGUA 22195450 | M12: Mant. y Raparacion Vehiculos Oper. | N12: 11001 | P12: FormaDePago | Q12: CodFormaDePago
A13: CF 02 | B13: 1021100001 | D13: Servicios | E13: SER | G13: FINANZAS | H13: FIN | J13: 0000007031 | K13: BOMBA DE AGUA JEEP VIASA 71 GT-43004 | M13: Reencauche de Llantas | N13: 11002 | P13: Contado | Q13: 001
A14: CF 03 | B14: 1021100002 | D14: SINIESTRO | E14: SNT | G14: FLOTA Y PATIO | H14: FP | J14: 0101015031 | K14: BOMBA DE AGUA NIS LD 28/Z20 GWN-05A | M14: Balanceo y Alineamiento de Llantas | N14: 11003 | P14: Factoring a 90 días. | Q14: 030
A15: CF 04 | B15: 1021100003 | D15: Serv.Terc.Ext. | E15: STE | G15: GERENCIA | H15: GER | J15: 0000006459 | K15: CARTER DE ACEITE FTL MB4000 A4600100213 | M15: Mant. y Raparacion Vehiculos Siniestrados. | N15: 11004 | P15: Pago 40 dias | Q15: 024
A16: CF BAJA | B16: 1021100004 | D16: Stocks de almacen | E16: STO | G16: LEGAL | H16: LEG | J16: 0000005459 | K16: FILTRO PARA POLVO 3M 7093 | M16: Franquicias Siniestros Operativos | N16: 1201 | P16: Pago 50 - 50 % | Q16: 031
A17: CF 06 | B17: 1021100005 | D17: Ventas | E17: VTA | G17: LOGISTICA Y ALMACEN | H17: ALM | J17: 0000009279 | K17: GABINETE PARED 8RU 42 X 53 X 53 SATRA | M17: Arreglo de Computadoras | N17: 13001 | P17: Pago a 1 Día | Q17: 005
A18: CF 09 | B18: 1021100006 | G18: MANTENIMIENTO | H18: MAN | J18: 0000004702 | K18: IPONLAC PRIMER CH (A+B) | M18: Mantenimiento equipos de oficina | N18: 13002 | P18: Pago a 10 Días | Q18: 015
A19: CF 08 | B19: 1021100008 | D19: Almacen | E19: AlmacenCodigo | G19: OPERACIONES | H19: OP | J19: 0000008795 | K19: LIMPIATAPIZ SAPOLIO | M19: Mantenimiento de Aire Acondicionado | N19: 13003 | P19: Pago a 12 Días | Q19: 016
A20: MOTONIV | B20: 1021200001 | D20: Almacén Trujillo | E20: A001 | G20: OPERACIONES PAITA | H20: OPA | J20: 1901999128 | K20: MATA TODO SAPOLIO | M20: Matenimiento Fotocopiadora | N20: 13004 | P20: Pago a 120 Días | Q20: 020
A21: RETROEX | B21: 1021300001 | D21: Almacén Lima | E21: A004 | G21: OPERACIONES PIURA | H21: OPI | J21: 0000005275 | K21: PEPSI COLA GARRAFA VIDRO 1250CX12 | M21: Pruebas Varias | N21: 1403 | P21: Pago a 15 Días | Q21: 003
A22: RODILLO | B22: 1021400001 | D22: Almacén Mina-Trujillo | E22: A005 | G22: PRODUCCION Y DISEÑO | H22: PRO | J22: 1699001158 | K22: PISTON 11144403 EMBRAGUE 3-4 | M22: Mantenimiento y reparacion de vh | N22: 1404 | P22: Pago a 150 Días | Q22: 150
A23: CUCHARON | B23: 1021500001 | D23: Almacén Commodities | E23: A007 | G23: RECEPCION | H23: REC | J23: 0000005052 | K23: PLAF LED | M23: Mantenimiento de local | N23: 1405 | P23: Pago a 154 Días | Q23: 021
A24: CUCHARON | B24: 1021500002 | D24: Almacén para Herramientas | E24: A008 | G24: RECURSOS HUMANOS | H24: RRH | J24: 0000004432 | K24: RADIADOR HOSE L120E 11410996 | M24: Trabajos Cisterna Combustible | N24: 1406 | P24: Pago a 180 Días | Q24: 026
A25: MONT 04 | B25: 1022100002 | D25: Almacen inmovilizado | E25: A009 | G25: SEGURIDAD | H25: SEG | J25: 0000006400 | K25: REDUCTOR 3/8 X 1/4 | M25: Instalación de Equipos Diversos | N25: 1601 | P25: Pago a 19 Días | Q25: 027
A26: MONT 06 | B26: 1022100003 | D26: Almacen Salaverry | E26: A010 | G26: SISTEMAS | H26: SIS | J26: 0000008467 | K26: REDUCTOR 3/8 X 1/8 | M26: Manten-Equipos, Maquinarias Diversos | N26: 1602 | P26: Pago a 2 Días | Q26: 006
A27: MONT 12 | B27: 1022100005 | D27: CAJA EMERGENCIAS | E27: A020 | J27: 0000008488 | K27: REDUCTOR HEMBRA 3/8 X 3/8 NPT | M27: Manten y Reparacion de Surtidor de Combustible | N27: 1603 | P27: Pago a 20 Días | Q27: 010
A28: MONT 14 | B28: 1022100006 | D28: PROVICIONAL CONDICION FLOTA | E28: A021 | G28: NombreCosto | H28: CentroCosto | J28: 0000007237 | K28: RODAJE KOYO 6201-2RSC3 | M28: Trabajos de repar. en el Surtidor de Combustible | N28: 1604 | P28: Pago a 21 Días | Q28: 028
A29: MONT 16 | B29: 1022100007 | D29: PRODUCTOS SEGUNDO USO | E29: A022 | G29: Gerencia de Operaciones | H29: 010101 | J29: 0000008227 | K29: SENSOR DE OXIGENO APV GC416 | M29: Mejoras- La Encalada | N29: 1701 | P29: Pago a 22 Días | Q29: 025
A30: MONT 18 | B30: 1022100008 | D30: ALMACEN ALTRA | E30: ALTRA | G30: Operaciones | H30: 010102 | J30: 0217001049 | K30: VALVULA DE ADMISION Y ESCAPE (Nissan-K25) | M30: Pintado de Fachada | N30: 19001 | P30: Pago a 23 Días | Q30: 029
A31: MONT 22 | B31: 1022100009 | D31: Almacen Ventas Trujillo | E31: AV01 | G31: Tractos | H31: 010201 | J31: 0000003057 | K31: VALVULA DE ADMISION Y ESCAPE PERKINS D728N | M31: Capacitacion Personal Administrativo | N31: 2701 | P31: Pago a 25 Días | Q31: 011
A32: MONT 24 | B32: 1022100010 | D32: Bra Materia Prima Trujillo | E32: BRA-M.PRIM | G32: Plataformas | H32: 010202 | J32: 0000004248 | K32: U DE PLASTICO | M32: Capacitacion Personal Conductores | N32: 2702 | P32: Pago a 3 Días | Q32: 007
A33: MONT 26 | B33: 1022100011 | D33: Consignación Consumo | E33: CONSIGNA01 | G33: Cortineras | H33: 010203 | J33: 0000006665 | K33: ¢ 83 E.O 2AL/INC AUXILIAR CONSERVERA | M33: pasajes nacionales | N33: 2801 | P33: Pago a 30 Dias | Q33: 004
A34: MONT 28 | B34: 1022100012 | D34: MERC. TRANSITO TRUJILLO | E34: T-TRANSITO | G34: Furgones | H34: 010204 | J34: 2301010075 | K34: ¢ 83 E.O 2AL/INC METALPREN | M34: Encomiendas | N34: 2802 | P34: Pago a 35 Días | Q34: 017
A35: SANTA CAT | B35: 1022100017 | G35: Tolvas | H35: 010205 | J35: 2301010076 | K35: ¢ 83 E.O 2DR/INC AUXILIAR CONSERVERA | M35: Flete Transporte Combustible | N35: 2803 | P35: Pago a 45 Días | Q35: 018
A36: MONT 30 | B36: 1022100018 | G36: Thermoking | H36: 010206 | J36: 2301010074 | K36: ¢ 83 E.O AL/DR METALPREN | M36: Flete Transporte Terceros | N36: 2804 | P36: Pago a 5 Días | Q36: 008
A37: MONT 32 | B37: 1022100019 | D37: Descripcion | E37: UnidadNegocio | G37: Contenedor | H37: 010207 | J37: 2301010077 | K37: ¢100 AL2/INC INESA | M37: FLETE ENCARGADO A TERCEROS | N37: 2805 | P37: Pago a 6 Días | Q37: 009
A38: MONT 33 | B38: 1022100020 | D38: AGENCIA DE ADUANAS | E38: AGEN | G38: Camabaja | H38: 010208 | J38: 2301010065 | K38: ¢65 E.O AL/INC AUX CONSER | M38: PEAJES | N38: 2806 | P38: Pago a 60 Días | Q38: 019
A39: MONT FGZN25 | B39: 1022100021 | D39: Servicio de Almacenaje | E39: ALMA | G39: Camioneta | H39: 010209 | J39: 2301010069 | K39: ¢65 E.O DR2/DR AUXILIAR CONSERVERA | M39: Instalaciones Electricas | N39: 3101 | P39: Pago a 7 Dias | Q39: 002
A40: PLATAF TIJE | B40: 1022100022 | D40: Maquinaria Pesada | E40: MAQU | G40: Camioncito | H40: 010210 | J40: 2301010066 | K40: ¢65 E.O DR2/DR METALPREN | M40: Mantenimiento de local | N40: 3102 | P40: Pago a 70 Días | Q40: 012
A41: TRANSPALETA | B41: 1022100023 | D41: VENTA DE PRODUCTOS VARIOS | E41: MERC | G41: Motocicleta | H41: 010211 | J41: 2301010067 | K41: ¢65 E.O DR2/INC AUXILIAR CONSERVERA | M41: Almacen La Encalada - Construcción | N41: 3103 | P41: Pago a 8 Días | Q41: 013
A42: P4D738 | B42: 1022100024 | D42: Servicio de Transporte de Carg | E42: TRAN | G42: Cuatrimoto | H42: 010212 | J42: 2301010068 | K42: ¢73 E.O 2DR/INC AUXILIAR CONSERVERA | M42: Nuevo Almacén - Larrea 1 | N42: 3104 | P42: Pago a 9 Días | Q42: 014
A43: T2A902 | B43: 1031100046 | G43: Servicio de Transporte Terceros | H43: 010213 | J43: 2301010070 | K43: ¢73 E.O 2DR/INC ECOACUICOLA | M43: Servicios de Construcción | N43: 3105 | P43: Pago a 90 Días | Q43: 022
A44: T2A908 | B44: 1031100047 | G44: Siniestros | H44: 010214 | J44: 2301010112 | K44: ¢73 E.O 2DR/INC METALPREN | M44: Mejoras - Construcciones Encalada | N44: 3106 | P44: pago en 50 dias | Q44: 023
A45: T2A909 | B45: 1031100048 | D45: DescripcionLocal | E45: CodigoDestino | G45: Cisterna de Combustible | H45: 010215 | J45: 2301010073 | K45: ¢73 E.O AL2/INC INESA | M45: Mejoras - Construcciones Larrea | N45: 3107
A46: T2A914 | B46: 1031100049 | D46: MURANO-2 W-214706 | E46: 214706 | G46: Cisternas Lima Gas | H46: 010216 | J46: 2301010072 | K46: ¢73 E.O DR2/INC INESA | M46: Construccion almacen Larrea3 | N46: 3108
A47: T2A915 | B47: 1031100050 | D47: MURANO-1 W-318979 | E47: 318979 | G47: Granos | H47: 010301 | J47: 2301010071 | K47: ¢99 3DR/INC AUXILIAR CONSERVERA | M47: Lineas Telefonia Celular | N47: 4001
A48: T2A916 | B48: 1031100051 | D48: Camioneta Montero 4E-3033 | E48: 4E3033 | G48: Fertilizantes | H48: 010302 | J48: 2301010064 | K48: ¢99 E.O 2DR/INC METALPREN | M48: Inspecciones Vehiculares | N48: 4201
A49: T2A918 | B49: 1031100052 | D49: Camioneta Kia Placa RD-6073 | E49: 6073 | G49: Estibas de granos | H49: 010303 | J49: 2301010079 | K49: ¢99 E.O 3DR/INC AUXILIAR CONSERVERA | M49: Asesoria Legal | N49: 4301
A50: T2A922 | B50: 1031100053 | D50: Camioneta Murano RD6267 | E50: 6267 | G50: Estibas de fertilizantes | H50: 010304 | J50: 2301010078 | K50: 17-14781-000-SSTP SEGURO GANCHO CAPOT(FTL) | M50: Asesoria Administrativas | N50: 4302
A51: T2A923 | B51: 1031100054 | D51: Camioneta Murano RD6311 | E51: 6311 | G51: Ensacado granos | H51: 010305 | J51: 0000007311 | K51: 20405847 VALVULA | M51: Servicio de Seleccion de Personal | N51: 4303
A52: T2O894 | B52: 1031100056 | D52: Areas | E52: Areas | G52: Ensacado fertilizantes | H52: 010306 | J52: 0000005598 | K52: 21679835 JUNTA | M52: Auditoria ISO | N52: 4304
A53: T2O902 | B53: 1031100057 | D53: Auto Toyota Corolla | E53: BD4944 | G53: Molienda con ensacado - granos | H53: 010307 | J53: 0000007058 | K53: 23 12734 160 FTL ABRAZADERA MUELLE | M53: MANTEN. EQUIPOS DE SEGURIDAD | N53: 8302
A54: T2O925 | B54: 1031100061 | D54: Carreta 001 | E54: C-001 | G54: Almacén | H54: 010308 | J54: 0000005321 | K54: 759900 OCEAN FOCO H7 24V. 70 W. (KOREA ORIGINAL) || 48728 | M54: MANTEN.EQUIPOS DE TALLER | N54: 8303
A55: T3A856 | B55: 1031100065 | D55: Carreta 02 | E55: CARRETA02 | G55: Balanza | H55: 010309 | J55: 0204003033 | K55: ABC ESCARCHADO N-6 | M55: ELABORACIÓN DE CAJAS DE REGALO | N55: 8304
A56: T3B836 | B56: 1031100066 | D56: Carreta 03 | E56: CARRETA03 | G56: Grupo Electrógeno | H56: 010310 | J56: 0000008235 | K56: ABONO MATCH 50 EC | M56: ATENCION A PERSONAL | N56: 8305
... A110: T8H889 | B110: 1031100267 | D110: Carreta ZD-3898 | E110: ZD3898 | G110: Logistica | H110: 060111 | J110: 0706001011 | K110: ABRAZADERA DE ACERO 24 X 4 X 9 | M110: SERVICIO EXPORTACION | N110: EX01
A111: T8N840 | B111: 1031100276 | D111: Carreta ZD-3899 | E111: ZD3899 | G111: Almacen General | H111: 060112 | J111: 0000009876 | K111: ABRAZADERA DE APRIETE EN ACERO INOX IDABLE
A112: T8N843 | B112: 1031100277 | D112: Carreta ZD-3980 | E112: ZD3980 | G112: Gerencia de Finanzas | H112: 060113 | J112: 0706001031 | K112: ABRAZADERA DE APRIETE EN ACERO INOX IDABLE
A113: T8N850 | B113: 1031100278 | D113: Carreta ZD-3981 | E113: ZD3981 | G113: AUDITORIA INTERNA | H113: 060114 | J113: 0000005763 | K113: ABRAZADERA DE MANGUERA 12485-250 FTL | M113: Descripcion | N113: Condicion
A114: T8N852 | B114: 1031100279 | D114: Carreta ZD-3982 | E114: ZD3982 | G114: LEGAL | H114: 060115 | J114: 0000005410 | K114: ABRAZADERA DE MUELLE DELANTERO 20560239 | M114: Nuevo | N114: 0
A115: T8N854 | B115: 1031100280 | D115: Carreta ZD-4017 | E115: ZD4017 | G115: Financieros | H115: 070101 | J115: 0509001015 | K115: ABRAZADERA DE MUELLE DELANTERO FH12/FM12 - 24x4x225 C/T | M115: Disponible | N115: 1
A116: T8N863 | B116: 1031100281 | D116: Carreta ZD-4143 | E116: ZD4143 | G116: Mantenimiento Carrocerias Propias | H116: 080101 | J116: 0000006563 | K116: ABRAZADERA DE MUELLE DELANTERO FH12/FM12 - 24x4x250 C/T | M116: Reciclado | N116: 2
A117: T8N872 | B117: 1031100282 | D117: Carreta ZD-4161 | E117: ZD4161 | G117: Mantenimiento Equipos Propios | H117: 080102 | J117: 0000006564 | K117: ABRAZADERA DE MUELLE DELANTERO RH 20529990 | M117: Malogrado - Merma | N117: 3
A118: T8Z865 | B118: 1031100283 | D118: Carreta ZD-4162 | E118: ZD4162 | G118: Mantenimiento Instalaciones Propias | H118: 080103 | J118: 0000005466 | K118: ABRAZADERA DE PAQUETE DE MUELLE L/D 20375243 | M118: Observado | N118: 4
A119: T8Z873 | B119: 1031100284 | D119: Carreta ZD-4163 | E119: ZD4163 | G119: TECNOLOGIAS EN MICROCONTROLADORES SAC | H119: 800000 | J119: 0000008717 | K119: ABRAZADERA DE PULMON DE AIRE 7"
A120: T8Z871 | B120: 1031100285 | D120: Carreta ZD-4173 | E120: ZD4173 | G120: CORPORACIÓN NOUBI SAC | H120: 800001 | J120: 0706001035 | K120: ABRAZADERA DE PULMON DE AIRE 8" | M120: Descripcion | N120: UnidadCodigo
A121: T8Z861 | B121: 1031100286 | D121: Carreta ZD-4179 | E121: ZD4179 | G121: DECOR MUEBLE SAC | H121: 800002 | J121: 0000002251 | K121: ABRAZADERA DE PULMON DE AIRE 9" | M121: Unidad | N121: UNI
A122: T8Z858 | B122: 1031100287 | D122: Carreta ZD-4197 | E122: ZD4197 | G122: YNG SAC | H122: 800003 | J122: 0000008716 | K122: ABRAZADERA GBS W1 104 - 112 ANCHA 4 -1/4 | M122: BIG BAG | N122: BGB
A123: T8Z878 | B123: 1031100288 | D123: Carreta ZD-4198 | E123: ZD4198 | G123: IBERICA DE MANTENIMIENTO S.A. SUCURSAL DEL PERU | H123: 800004 | J123: 0000000461 | K123: ABRAZADERA INDUSTRIAL 122 - 130 mm | M123: Bidón | N123: BID
A124: T8Z872 | B124: 1031100289 | D124: Carreta ZD-4299 | E124: ZD4299 | G124: HIELOSNORTE S.A.C. | H124: 800005 | J124: 0000000866 | K124: ABRAZADERA INDUSTRIAL T-509 | M124: BOLSA X 1.00 KG | N124: BL1
A125: T8Z853 | B125: 1031100290 | D125: Carreta ZD-4300 | E125: ZD4300 | G125: BIOPROTECK S.A.C. | H125: 800006 | J125: 0000002579 | K125: ABRAZADERA NORMA 3 '' TS T12/W1 70-90 | M125: BOLSA X 0.50 KG | N125: BL2
A126: T8Z864 | B126: 1031100291 | D126: Carreta ZD-4301 | E126: ZD4301 | G126: TVT PERU SAC | H126: 800007 | J126: 0000008911 | K126: ABRAZADERA P/ TUBO DE 1" | M126: Bolsa | N126: BOL
A127: T8Z875 | B127: 1031100292 | D127: Carreta ZD-4302 | E127: ZD4302 | G127: BANCO BBVA PERU | H127: 800008 | J127: 0000007654 | K127: ABRAZADERA P/MANGUERA 16-27 NORMA | M127: Botella | N127: BOT
A128: T8Z874 | B128: 1031100293 | D128: Carreta ZD-4303 | E128: ZD4303 | G128: CONEXION CARGO S.A.C. | H128: 800009 | J128: 0000009028 | K128: ABRAZADERA P/MANGUERA INTERCOOLER INTERNATIONAL 1517672C91 | M128: BULTO | N128: BUL
A129: T8Z852 | B129: 1031100294 | D129: Carreta ZD-4304 | E129: ZD4304 | G129: TALMA SERVICIOS AEROPORTUARIOS S.A | H129: 800010 | J129: 0706001036 | K129: ABRAZADERA P/RIEL 1 - 1/4" | M129: Caja- Solo Ida | N129: CI
A130: T8Z876 | B130: 1031100295 | D130: Carreta ZD-4335 | E130: ZD4335 | G130: TVT-CONEXION CARGO | H130: 800011 | J130: 0000000456 | K130: ABRAZADERA PARA INTERCOOLER FTL CL120 BRZ B9224 0411FRU | M130: Cilindro | N130: CIL
A131: T8Z877 | B131: 1031100297 | D131: Carreta ZD-4338 | E131: ZD4338 | G131: GREEN PERU S.A. | H131: 800012 | J131: 0000000457 | K131: ABRAZADERA PARA TUBO 2" ( 2 OREJAS ) | M131: Caja | N131: CJ
... A149: T9R833 | B149: 1031100315 | D149: Carreta con Baranda ZD-4792 | E149: ZD4792 | G149: IMPORT & EXPORT JAEN S.A.C. | H149: 800030 | J149: 0000001251 | K149: ACCESORIO DE SELECTOR CAJA SR1700 SLP 3094465 | M149: Metro | N149: MT
A150: T9R868 | B150: 1031100316 | D150: Carreta ZD-4794 | E150: ZD4794 | J150: 0000010009 | K150: ACCESORIO DE TIMON 8098 | M150: METROS CUADRADOS | N150: MT2
A151: T9R931 | B151: 1031100317 | D151: Carreta ZD-4795 | E151: ZD4795 | J151: 0611999031 | K151: ACCESORIO DE VALVULA DE DESFOGUE AIRE FTL 50 MM. | M151: Metros Cúbicos | N151: MT3
A152: T9G904 | B152: 1031100318 | D152: Carreta ZD-4796 | E152: ZD4796 | J152: 0000006020 | K152: ACCESORIO DE VALVULA SIMPLE 1-1/4 | M152: PAQUETE x 24.00 KG | N152: PA1
A153: T9G939 | B153: 1031100319 | D153: Carreta ZD-4835 | E153: ZD4835 | G153: Descripcion | H153: Referencia | J153: 0301999018 | K153: ACCESORIO ELECTROVALVULA CILINDRO SELECTOR VOLVO 400 | M153: PAQUETE x 25.00 KG | N153: PA2
A154: T9G939 | B154: 1031100319 | D154: Carreta ZD-4838 | E154: ZD4838 | G154: FACTURACION | H154: 100 | J154: 0000006784 | K154: ACCESORIO MANOS LIBRES MOTOROLA PARA MOVIL MOD. AARMN4027 y | M154: PAQUETE x 50.00 KG | N154: PA3
A155: T9H805 | B155: 1031100320 | D155: Carreta ZD-4839 | E155: ZD4839 | G155: CONTR. COMBUST. Y G.V | H155: 101 | J155: 0000007157 | K155: ACCESORIO P/TANQUE BAJO 7/8 | M155: PAQUETE X 10.00 KG | N155: PA4
A156: T9H805 | B156: 1031100320 | D156: Carreta ZD-4840 | E156: ZD4840 | G156: GERENCIA OPERACIONES | H156: 102 | J156: 0000008599 | K156: ACCESORIO PARA INGRESO DE AGUA - INODORO | M156: Pallets | N156: PAL
A157: TAD852 | B157: 1031100321 | D157: Carreta ZD-4842 | E157: ZD4842 | G157: ADMINISTRAC. LIMA | H157: 103 | J157: 0000008598 | K157: ACCESORIO T R E N D N E T ® T U - S 9 INTERFAZ USB-232 | M157: Paquete | N157: PAQ
A158: TAD850 | B158: 1031100322 | D158: Carreta ZD-4843 | E158: ZD4843 | G158: OPERACIONES LIMA | H158: 104 | J158: 0000007099 | K158: ACCESORIOS DE FRENO MANO | M158: Pares | N158: PAR
A159: TAD844 | B159: 1031100323 | D159: Careta ZD-4847 | E159: ZD4847 | G159: LA ENCALADA | H159: 105 | J159: 0101015029 | K159: ACCESORIOS DE FRENO POST( 314147) | M159: Pies | N159: PIE
A160: TAD868 | B160: 1031100324 | D160: Carreta ZD-4848 | E160: ZD4848 | G160: FUNDO LA REA | H160: 106 | J160: 0401999020 | K160: ACCESS POINT TP-LINK EAP225-OUTDOOR, 1200 MBPS, DUAL BAND, 8 | M160: Ploteo | N160: PL
A161: TAD874 | B161: 1031100325 | D161: Carreta ZD-4850 | E161: ZD4850 | G161: RECURSOS HUMANOS | H161: 107 | J161: 0301999007 | K161: ACEITE 3 EN 1 EN FRASCO DE 80ML | M161: Pote | N161: POT
A162: TAD873 | B162: 1031100326 | D162: Carreta ZD-4851 | E162: ZD4851 | G162: CONTROL DE FLOTA | H162: 108 | J162: 0000007457 | K162: ACEITE 3 EN 1 EN FRASCO DE 90ML | M162: Pulgada | N162: PUL
A163: TAD887 | B163: 1031100327 | D163: Furgon ZD-5033 | E163: ZD5033 | G163: ALMACEN TRUJILLO | H163: 109 | J163: 0000008504 | K163: ACEITE 4 EN UNO | M163: Pieza | N163: PZA
A164: TAD889 | B164: 1031100328 | D164: Carreta ZD-5269 | E164: ZD5269 | G164: ALMACEN LIMA | H164: 110 | J164: 0112001001 | K164: ACEITE AEROSHELL FLUID 41 | M164: Rollo | N164: RLL
A165: TAD876 | B165: 1031100329 | D165: Carreta ZD-5272 | E165: ZD5272 | G165: SEGURIDAD | H165: 111 | J165: 0101016022 | K165: ACEITE CAJA DIRECCION ATF MD-3-PORSCHE | M165: Saco | N165: SC
... A178: T9G844 | B178: 1031100337 | D178: Furgon Metalico ZD-5466 | E178: ZD5466 | G178: MANTENIMIENTO | H178: 96 | J178: 1004001014 | K178: ACEITE GASOL 10W/30 0888070015 | M178: Vuelta | N178: VUE
A179: ADT905 | B179: 1031100338 | D179: Cortinero ZD-5467 | E179: ZD5467 | G179: VIGILANCIA | H179: 97 | J179: 1004001001 | K179: ACEITE GASOL 10W/30 0888070016
A180: ADT925 | B180: 1031100339 | D180: Cortinero ZD-5468 | E180: ZD5468 | G180: GERENCIA | H180: 98 | J180: 0000008193 | K180: ACEITE GULF HARMONY AW 68
A181: ADT854 | B181: 1031100340 | D181: Furgon Metalico ZD-5469 | E181: ZD5469 | G181: FINANZAS | H181: 99 | J181: 1001001024 | K181: ACEITE GULF MAX SAE 10W 30
A182: ADV877 | B182: 1031100341 | D182: Furgon Cortinero ZD-5724 | E182: ZD5724 | J182: 0000004620 | K182: ACEITE GULF UNIV TRACTOR TRANSMISSION FLUID SAE 85W(55GLN)
...
